{"ingresos_salidas":[{"@odata.etag":"","ItemInternalId":"7f750a86-cacc-4ec8-ae66-b915db68b134","Año":"2025","Mes":"1","Unidad":"Minera Casma","ALTAS":"40","BAJAS":"22","HC inicial":"341","HC final":"359","HC promedio":"350"},{"@odata.etag":"","ItemInternalId":"9d688158-6377-491d-9c60-10bc950935b0","Año":"2025","Mes":"1","Unidad":"Sede Mina","ALTAS":"4","BAJAS":"10","HC inicial":"61","HC final":"55","HC promedio":"58"},{"@odata.etag":"","ItemInternalId":"1ff95824-346c-4446-a1ad-1621cf85a232","Año":"2025","Mes":"1","Unidad":"Planta Beneficio","ALTAS":"11","BAJAS":"16","HC inicial":"172","HC final":"167","HC promedio":"169.5"},{"@odata.etag":"","ItemInternalId":"93b7b46c-7907-45c5-9632-c9106da76d89","Año":"2025","Mes":"1","Unidad":"Minera Onoaga","ALTAS":"4","BAJAS":"5","HC inicial":"37","HC final":"36","HC promedio":"36.5"},{"@odata.etag":"","ItemInternalId":"420eef1f-a2cf-4194-8695-4d57f8c94e45","Año":"2025","Mes":"1","Unidad":"Proyecto Puno","ALTAS":"0","BAJAS":"0","HC inicial":"0","HC final":"0","HC promedio":"0"},{"@odata.etag":"","ItemInternalId":"15abaa58-8e15-424a-9747-7b3a453e0c59","Año":"2025","Mes":"1","Unidad":"Proyecto Ariel","ALTAS":"0","BAJAS":"0","HC inicial":"0","HC final":"0","HC promedio":"0"},{"@odata.etag":"","ItemInternalId":"9603454f-abd8-454e-94a3-88b154ba3a47","Año":"2025","Mes":"2","Unidad":"Minera Casma","ALTAS":"53","BAJAS":"32","HC inicial":"359","HC final":"380","HC promedio":"369.5"},{"@odata.etag":"","ItemInternalId":"7d18e42b-70de-420a-bcc8-639592de1bbf","Año":"2025","Mes":"2","Unidad":"Sede Mina","ALTAS":"5","BAJAS":"4","HC inicial":"55","HC final":"56","HC promedio":"55.5"},{"@odata.etag":"","ItemInternalId":"e04a528c-e48b-4edd-babd-ba413ccbc473","Año":"2025","Mes":"2","Unidad":"Planta Beneficio","ALTAS":"14","BAJAS":"6","HC inicial":"167","HC final":"175","HC promedio":"171"},{"@odata.etag":"","ItemInternalId":"04f59402-5c4c-4e25-a668-2871f0a02dd7","Año":"2025","Mes":"2","Unidad":"Minera Onoaga","ALTAS":"4","BAJAS":"3","HC inicial":"36","HC final":"37","HC promedio":"36.5"},{"@odata.etag":"","ItemInternalId":"fd0a44bc-4806-4052-894d-ce2928c13aaa","Año":"2025","Mes":"2","Unidad":"Proyecto Puno","ALTAS":"5","BAJAS":"0","HC inicial":"0","HC final":"5","HC promedio":"2.5"},{"@odata.etag":"","ItemInternalId":"c6b70c3b-dba2-4a9c-9d9f-908bb2269ece","Año":"2025","Mes":"2","Unidad":"Proyecto Ariel","ALTAS":"0","BAJAS":"0","HC inicial":"0","HC final":"0","HC promedio":"0"},{"@odata.etag":"","ItemInternalId":"a7559ff6-6852-4888-8847-121f6064c7b0","Año":"2025","Mes":"3","Unidad":"Minera Casma","ALTAS":"67","BAJAS":"30","HC inicial":"380","HC final":"417","HC promedio":"398.5"},{"@odata.etag":"","ItemInternalId":"847fbd91-2cc7-4494-810c-0b471bd4731f","Año":"2025","Mes":"3","Unidad":"Sede Mina","ALTAS":"5","BAJAS":"10","HC inicial":"56","HC final":"51","HC promedio":"53.5"},{"@odata.etag":"","ItemInternalId":"3a2e58a5-0535-4ebe-8229-4a71de29aae4","Año":"2025","Mes":"3","Unidad":"Planta Beneficio","ALTAS":"10","BAJAS":"6","HC inicial":"175","HC final":"179","HC promedio":"177"},{"@odata.etag":"","ItemInternalId":"daf1a6be-30ec-4799-9310-e9a4aeeae210","Año":"2025","Mes":"3","Unidad":"Minera Onoaga","ALTAS":"7","BAJAS":"4","HC inicial":"37","HC final":"40","HC promedio":"38.5"},{"@odata.etag":"","ItemInternalId":"d3cb324c-9878-4e2f-8e1b-58c6d39db571","Año":"2025","Mes":"3","Unidad":"Proyecto Puno","ALTAS":"1","BAJAS":"0","HC inicial":"5","HC final":"6","HC promedio":"5.5"},{"@odata.etag":"","ItemInternalId":"9429b00e-491e-46c3-8f47-9c21fa529938","Año":"2025","Mes":"3","Unidad":"Proyecto Ariel","ALTAS":"0","BAJAS":"0","HC inicial":"0","HC final":"0","HC promedio":"0"},{"@odata.etag":"","ItemInternalId":"8cd84d72-b359-49e4-80d3-fbf3aa11045c","Año":"2025","Mes":"4","Unidad":"Minera Casma","ALTAS":"62","BAJAS":"29","HC inicial":"417","HC final":"450","HC promedio":"433.5"},{"@odata.etag":"","ItemInternalId":"2ae7fc85-6c2a-4ee8-b66a-54c0cc61ff43","Año":"2025","Mes":"4","Unidad":"Sede Mina","ALTAS":"12","BAJAS":"5","HC inicial":"51","HC final":"58","HC promedio":"54.5"},{"@odata.etag":"","ItemInternalId":"bb51a55c-fb86-4cc0-8a5f-5bf94ef410b3","Año":"2025","Mes":"4","Unidad":"Planta Beneficio","ALTAS":"0","BAJAS":"5","HC inicial":"179","HC final":"174","HC promedio":"176.5"},{"@odata.etag":"","ItemInternalId":"0cfcf3ab-0ac0-4c7d-b7be-ac0b2c155b68","Año":"2025","Mes":"4","Unidad":"Minera Onoaga","ALTAS":"0","BAJAS":"5","HC inicial":"40","HC final":"35","HC promedio":"37.5"},{"@odata.etag":"","ItemInternalId":"734c4fdc-b45d-444d-ad01-022410a3628e","Año":"2025","Mes":"4","Unidad":"Proyecto Puno","ALTAS":"0","BAJAS":"0","HC inicial":"6","HC final":"6","HC promedio":"6"},{"@odata.etag":"","ItemInternalId":"06e09038-4bbc-47c2-8a21-279319f8ef84","Año":"2025","Mes":"4","Unidad":"Proyecto Ariel","ALTAS":"0","BAJAS":"0","HC inicial":"0","HC final":"0","HC promedio":"0"},{"@odata.etag":"","ItemInternalId":"bab3b09b-37ea-406e-9504-2ff97ba3b1ba","Año":"2025","Mes":"5","Unidad":"Minera Casma","ALTAS":"32","BAJAS":"34","HC inicial":"450","HC final":"448","HC promedio":"449"},{"@odata.etag":"","ItemInternalId":"d54515ce-df54-4bf7-a829-a170728ad745","Año":"2025","Mes":"5","Unidad":"Sede Mina","ALTAS":"9","BAJAS":"9","HC inicial":"58","HC final":"58","HC promedio":"58"},{"@odata.etag":"","ItemInternalId":"a68e8ec4-6058-43fb-9e7a-b13f0d03eb64","Año":"2025","Mes":"5","Unidad":"Planta Beneficio","ALTAS":"5","BAJAS":"10","HC inicial":"174","HC final":"169","HC promedio":"171.5"},{"@odata.etag":"","ItemInternalId":"8f7b7624-e807-41a1-bcad-545d2fe7c9ae","Año":"2025","Mes":"5","Unidad":"Minera Onoaga","ALTAS":"7","BAJAS":"2","HC inicial":"35","HC final":"40","HC promedio":"37.5"},{"@odata.etag":"","ItemInternalId":"3b1f423b-d959-4b80-82d8-3915d099309f","Año":"2025","Mes":"5","Unidad":"Proyecto Puno","ALTAS":"0","BAJAS":"0","HC inicial":"6","HC final":"6","HC promedio":"6"},{"@odata.etag":"","ItemInternalId":"ccd09dc3-fe9f-4283-a09d-a9b4a20f393a","Año":"2025","Mes":"5","Unidad":"Proyecto Ariel","ALTAS":"0","BAJAS":"0","HC inicial":"0","HC final":"0","HC promedio":"0"},{"@odata.etag":"","ItemInternalId":"c43d0b66-8e50-4024-99fc-c75da80cede0","Año":"2025","Mes":"6","Unidad":"Minera Casma","ALTAS":"38","BAJAS":"17","HC inicial":"448","HC final":"469","HC promedio":"458.5"},{"@odata.etag":"","ItemInternalId":"d8c43e9e-a77f-43d0-8331-00016ebeab2b","Año":"2025","Mes":"6","Unidad":"Sede Mina","ALTAS":"11","BAJAS":"3","HC inicial":"58","HC final":"66","HC promedio":"62"},{"@odata.etag":"","ItemInternalId":"3d894abd-3c5b-4772-8378-3d1262826132","Año":"2025","Mes":"6","Unidad":"Planta Beneficio","ALTAS":"11","BAJAS":"6","HC inicial":"169","HC final":"174","HC promedio":"171.5"},{"@odata.etag":"","ItemInternalId":"f7b4d2e7-cebd-4797-9927-9bcdeec01137","Año":"2025","Mes":"6","Unidad":"Minera Onoaga","ALTAS":"5","BAJAS":"0","HC inicial":"40","HC final":"45","HC promedio":"42.5"},{"@odata.etag":"","ItemInternalId":"32ed97ca-64ce-4297-b0a0-a4714df0923a","Año":"2025","Mes":"6","Unidad":"Proyecto Puno","ALTAS":"0","BAJAS":"0","HC inicial":"6","HC final":"6","HC promedio":"6"},{"@odata.etag":"","ItemInternalId":"f85d91fe-9c0a-4be5-8f88-3ecc21ed035f","Año":"2025","Mes":"6","Unidad":"Proyecto Ariel","ALTAS":"0","BAJAS":"0","HC inicial":"0","HC final":"0","HC promedio":"0"},{"@odata.etag":"","ItemInternalId":"a6fc3adb-34f4-469b-9672-8438c6d8ec63","Año":"2025","Mes":"7","Unidad":"Minera Casma","ALTAS":"47","BAJAS":"38","HC inicial":"469","HC final":"478","HC promedio":"473.5"},{"@odata.etag":"","ItemInternalId":"3ade31e3-99fc-4651-b6a3-cdb46621022c","Año":"2025","Mes":"7","Unidad":"Sede Mina","ALTAS":"3","BAJAS":"2","HC inicial":"66","HC final":"67","HC promedio":"66.5"},{"@odata.etag":"","ItemInternalId":"09115ae9-e09a-422f-ae09-e84d05a3466e","Año":"2025","Mes":"7","Unidad":"Planta Beneficio","ALTAS":"6","BAJAS":"8","HC inicial":"174","HC final":"172","HC promedio":"173"},{"@odata.etag":"","ItemInternalId":"83bfedf7-440d-4249-b3f4-5f31cab52e0e","Año":"2025","Mes":"7","Unidad":"Minera Onoaga","ALTAS":"3","BAJAS":"3","HC inicial":"45","HC final":"45","HC promedio":"45"},{"@odata.etag":"","ItemInternalId":"605e0270-76d2-4154-a1d6-4d2544b4022c","Año":"2025","Mes":"7","Unidad":"Proyecto Puno","ALTAS":"0","BAJAS":"0","HC inicial":"6","HC final":"6","HC promedio":"6"},{"@odata.etag":"","ItemInternalId":"c33eff54-6386-4e6f-bd61-aa6b799f4994","Año":"2025","Mes":"7","Unidad":"Proyecto Ariel","ALTAS":"0","BAJAS":"0","HC inicial":"0","HC final":"0","HC promedio":"0"},{"@odata.etag":"","ItemInternalId":"f778e277-62c1-43cf-8443-41dda9163f44","Año":"2025","Mes":"8","Unidad":"Minera Casma","ALTAS":"70","BAJAS":"44","HC inicial":"478","HC final":"504","HC promedio":"491"},{"@odata.etag":"","ItemInternalId":"73cf1a3f-7cdd-4bfb-9b51-434fbc5604c0","Año":"2025","Mes":"8","Unidad":"Sede Mina","ALTAS":"5","BAJAS":"4","HC inicial":"67","HC final":"68","HC promedio":"67.5"},{"@odata.etag":"","ItemInternalId":"e0de9c56-ebd2-49c8-aae5-af96befad31e","Año":"2025","Mes":"8","Unidad":"Planta Beneficio","ALTAS":"12","BAJAS":"11","HC inicial":"172","HC final":"173","HC promedio":"172.5"},{"@odata.etag":"","ItemInternalId":"8b7c6486-89fa-4450-a51c-f91863c751ee","Año":"2025","Mes":"8","Unidad":"Minera Onoaga","ALTAS":"9","BAJAS":"6","HC inicial":"45","HC final":"48","HC promedio":"46.5"},{"@odata.etag":"","ItemInternalId":"fffe4e28-8c85-4c7d-8dc0-9ff763a0028d","Año":"2025","Mes":"8","Unidad":"Proyecto Puno","ALTAS":"0","BAJAS":"1","HC inicial":"6","HC final":"5","HC promedio":"5.5"},{"@odata.etag":"","ItemInternalId":"b94d4bf0-1ebf-47d0-84fb-1baa86a24d15","Año":"2025","Mes":"8","Unidad":"Proyecto Ariel","ALTAS":"0","BAJAS":"0","HC inicial":"0","HC final":"0","HC promedio":"0"},{"@odata.etag":"","ItemInternalId":"607bf555-20eb-4c1d-b9f2-b05452d6d89e","Año":"2025","Mes":"9","Unidad":"Minera Casma","ALTAS":"42","BAJAS":"27","HC inicial":"504","HC final":"519","HC promedio":"511.5"},{"@odata.etag":"","ItemInternalId":"0fd08946-19ef-4e22-a7e0-aaaf7de85998","Año":"2025","Mes":"9","Unidad":"Sede Mina","ALTAS":"8","BAJAS":"12","HC inicial":"68","HC final":"64","HC promedio":"66"},{"@odata.etag":"","ItemInternalId":"0e24f632-86b3-419e-9783-131fedd2fd3f","Año":"2025","Mes":"9","Unidad":"Planta Beneficio","ALTAS":"5","BAJAS":"0","HC inicial":"173","HC final":"178","HC promedio":"175.5"},{"@odata.etag":"","ItemInternalId":"4e1165fa-ea4b-463b-b710-e079743109b3","Año":"2025","Mes":"9","Unidad":"Minera Onoaga","ALTAS":"5","BAJAS":"3","HC inicial":"48","HC final":"50","HC promedio":"49"},{"@odata.etag":"","ItemInternalId":"1a8eeab1-f6a8-4ba4-a160-6cd4c3073c9c","Año":"2025","Mes":"9","Unidad":"Proyecto Puno","ALTAS":"1","BAJAS":"1","HC inicial":"5","HC final":"5","HC promedio":"5"},{"@odata.etag":"","ItemInternalId":"8d6db6c2-5fa7-4c65-b052-482dcfd6be41","Año":"2025","Mes":"9","Unidad":"Proyecto Ariel","ALTAS":"0","BAJAS":"0","HC inicial":"0","HC final":"0","HC promedio":"0"},{"@odata.etag":"","ItemInternalId":"fc672578-40da-4ce1-befc-d05d2d2130cb","Año":"2025","Mes":"10","Unidad":"Minera Casma","ALTAS":"35","BAJAS":"44","HC inicial":"519","HC final":"510","HC promedio":"514.5"},{"@odata.etag":"","ItemInternalId":"065c36a7-fb64-40d0-bc19-eeb825342c29","Año":"2025","Mes":"10","Unidad":"Sede Mina","ALTAS":"13","BAJAS":"4","HC inicial":"64","HC final":"73","HC promedio":"68.5"},{"@odata.etag":"","ItemInternalId":"a41f1a78-05a6-45fb-9c51-7234eb704656","Año":"2025","Mes":"10","Unidad":"Planta Beneficio","ALTAS":"1","BAJAS":"9","HC inicial":"178","HC final":"170","HC promedio":"174"},{"@odata.etag":"","ItemInternalId":"d23daf9a-218e-4a7a-8af7-1f4218874888","Año":"2025","Mes":"10","Unidad":"Minera Onoaga","ALTAS":"8","BAJAS":"2","HC inicial":"50","HC final":"56","HC promedio":"53"},{"@odata.etag":"","ItemInternalId":"1c1c5367-ce0c-4a41-a129-4108f703bd43","Año":"2025","Mes":"10","Unidad":"Proyecto Puno","ALTAS":"1","BAJAS":"0","HC inicial":"5","HC final":"6","HC promedio":"5.5"},{"@odata.etag":"","ItemInternalId":"4add1e03-46ce-4d5d-bcaa-7ee2633c04ec","Año":"2025","Mes":"10","Unidad":"Proyecto Ariel","ALTAS":"0","BAJAS":"0","HC inicial":"0","HC final":"0","HC promedio":"0"},{"@odata.etag":"","ItemInternalId":"8a40004a-2660-4305-8cba-6d4b432f1601","Año":"2025","Mes":"11","Unidad":"Minera Casma","ALTAS":"36","BAJAS":"37","HC inicial":"510","HC final":"509","HC promedio":"509.5"},{"@odata.etag":"","ItemInternalId":"70ba4b59-91b7-46e8-8373-6fb3dca85919","Año":"2025","Mes":"11","Unidad":"Sede Mina","ALTAS":"4","BAJAS":"2","HC inicial":"73","HC final":"75","HC promedio":"74"},{"@odata.etag":"","ItemInternalId":"f6052e1a-3209-40d1-9969-03d1d95a343f","Año":"2025","Mes":"11","Unidad":"Planta Beneficio","ALTAS":"4","BAJAS":"7","HC inicial":"170","HC final":"167","HC promedio":"168.5"},{"@odata.etag":"","ItemInternalId":"be7310fc-f57c-4e00-9321-70f6fc422887","Año":"2025","Mes":"11","Unidad":"Minera Onoaga","ALTAS":"9","BAJAS":"6","HC inicial":"56","HC final":"59","HC promedio":"57.5"},{"@odata.etag":"","ItemInternalId":"7162462a-90bd-4eb9-92cc-90ad0a0cb75e","Año":"2025","Mes":"11","Unidad":"Proyecto Puno","ALTAS":"0","BAJAS":"0","HC inicial":"6","HC final":"6","HC promedio":"6"},{"@odata.etag":"","ItemInternalId":"a671cec8-a119-4aed-83f9-ca1b27786710","Año":"2025","Mes":"11","Unidad":"Proyecto Ariel","ALTAS":"0","BAJAS":"0","HC inicial":"0","HC final":"0","HC promedio":"0"},{"@odata.etag":"","ItemInternalId":"9228a330-d6f8-4bd8-8517-86b3bbfe82df","Año":"2025","Mes":"12","Unidad":"Minera Casma","ALTAS":"22","BAJAS":"61","HC inicial":"509","HC final":"470","HC promedio":"489.5"},{"@odata.etag":"","ItemInternalId":"f98e56f2-6629-4730-a857-eaffbea934eb","Año":"2025","Mes":"12","Unidad":"Sede Mina","ALTAS":"7","BAJAS":"9","HC inicial":"75","HC final":"73","HC promedio":"74"},{"@odata.etag":"","ItemInternalId":"6c16c914-33df-4779-8748-33a2a3931c52","Año":"2025","Mes":"12","Unidad":"Planta Beneficio","ALTAS":"6","BAJAS":"3","HC inicial":"167","HC final":"170","HC promedio":"168.5"},{"@odata.etag":"","ItemInternalId":"1ed2ab30-b44d-4f6c-bfa8-a7141a658646","Año":"2025","Mes":"12","Unidad":"Minera Onoaga","ALTAS":"4","BAJAS":"3","HC inicial":"59","HC final":"60","HC promedio":"59.5"},{"@odata.etag":"","ItemInternalId":"1b4d2c89-41bc-4dbc-99fd-6f2ed108ced9","Año":"2025","Mes":"12","Unidad":"Proyecto Puno","ALTAS":"0","BAJAS":"0","HC inicial":"6","HC final":"6","HC promedio":"6"},{"@odata.etag":"","ItemInternalId":"bf7cb817-ab2e-4978-b598-cca4111e0984","Año":"2025","Mes":"12","Unidad":"Proyecto Ariel","ALTAS":"0","BAJAS":"0","HC inicial":"0","HC final":"0","HC promedio":"0"},{"@odata.etag":"","ItemInternalId":"f8810ae2-7a0b-476a-a6fb-b9aeafe1bfb9","Año":"2026","Mes":"1","Unidad":"Minera Casma","ALTAS":"61","BAJAS":"44","HC inicial":"470","HC final":"487","HC promedio":"478.5"},{"@odata.etag":"","ItemInternalId":"6e5fbea7-ddf5-4770-8e9b-3cedf374f07b","Año":"2026","Mes":"1","Unidad":"Sede Mina","ALTAS":"5","BAJAS":"6","HC inicial":"73","HC final":"72","HC promedio":"72.5"},{"@odata.etag":"","ItemInternalId":"9f734e2b-410d-4b89-9296-d1bf0841046b","Año":"2026","Mes":"1","Unidad":"Planta Beneficio","ALTAS":"14","BAJAS":"7","HC inicial":"170","HC final":"177","HC promedio":"173.5"},{"@odata.etag":"","ItemInternalId":"a9c7fdb2-5164-40ef-8519-99480eeb4fdd","Año":"2026","Mes":"1","Unidad":"Minera Onoaga","ALTAS":"13","BAJAS":"7","HC inicial":"60","HC final":"66","HC promedio":"63"},{"@odata.etag":"","ItemInternalId":"73f3fe60-0f7d-45df-b905-b2c4c1f15a74","Año":"2026","Mes":"1","Unidad":"Proyecto Puno","ALTAS":"0","BAJAS":"1","HC inicial":"6","HC final":"5","HC promedio":"5.5"},{"@odata.etag":"","ItemInternalId":"fbdabd38-f8dc-4030-9dab-56ae08a7e47c","Año":"2026","Mes":"1","Unidad":"Proyecto Ariel","ALTAS":"0","BAJAS":"0","HC inicial":"0","HC final":"0","HC promedio":"0"},{"@odata.etag":"","ItemInternalId":"8138d8e5-8cfc-456e-9c1d-ee00e44f87fb","Año":"2026","Mes":"2","Unidad":"Minera Casma","ALTAS":"54","BAJAS":"32","HC inicial":"487","HC final":"509","HC promedio":"498"},{"@odata.etag":"","ItemInternalId":"4c43f8d0-2634-4fd6-b73e-812474daf6c3","Año":"2026","Mes":"2","Unidad":"Sede Mina","ALTAS":"11","BAJAS":"3","HC inicial":"72","HC final":"80","HC promedio":"76"},{"@odata.etag":"","ItemInternalId":"56474fb9-bbed-457d-bcf9-c9d4903bc5a5","Año":"2026","Mes":"2","Unidad":"Planta Beneficio","ALTAS":"11","BAJAS":"9","HC inicial":"177","HC final":"179","HC promedio":"178"},{"@odata.etag":"","ItemInternalId":"8a9b25e8-3698-4741-b5fa-04bac6725aa6","Año":"2026","Mes":"2","Unidad":"Minera Onoaga","ALTAS":"9","BAJAS":"7","HC inicial":"66","HC final":"68","HC promedio":"67"},{"@odata.etag":"","ItemInternalId":"1eafb33b-dddf-469c-b274-61a472d8d820","Año":"2026","Mes":"2","Unidad":"Proyecto Puno","ALTAS":"0","BAJAS":"0","HC inicial":"5","HC final":"5","HC promedio":"5"},{"@odata.etag":"","ItemInternalId":"6da0335e-b01c-46a0-9bad-f5c8629ced68","Año":"2026","Mes":"2","Unidad":"Proyecto Ariel","ALTAS":"0","BAJAS":"0","HC inicial":"0","HC final":"0","HC promedio":"0"},{"@odata.etag":"","ItemInternalId":"95640b32-20d3-4ccd-bc4b-3cbb78694175","Año":"2026","Mes":"3","Unidad":"Minera Casma","ALTAS":"61","BAJAS":"43","HC inicial":"509","HC final":"527","HC promedio":"518"},{"@odata.etag":"","ItemInternalId":"2578a8bb-3ab3-4702-857f-ce7343e3cf5e","Año":"2026","Mes":"3","Unidad":"Sede Mina","ALTAS":"11","BAJAS":"3","HC inicial":"80","HC final":"88","HC promedio":"84"},{"@odata.etag":"","ItemInternalId":"34b2b037-915e-45f7-96ae-ca44d99bfa13","Año":"2026","Mes":"3","Unidad":"Planta Beneficio","ALTAS":"10","BAJAS":"8","HC inicial":"179","HC final":"181","HC promedio":"180"},{"@odata.etag":"","ItemInternalId":"b2046a81-5ec3-42ce-8e08-ec2d9836834d","Año":"2026","Mes":"3","Unidad":"Minera Onoaga","ALTAS":"17","BAJAS":"10","HC inicial":"68","HC final":"75","HC promedio":"71.5"},{"@odata.etag":"","ItemInternalId":"51d9015d-a568-48c9-8e4b-89621c106e45","Año":"2026","Mes":"3","Unidad":"Proyecto Puno","ALTAS":"0","BAJAS":"0","HC inicial":"5","HC final":"5","HC promedio":"5"},{"@odata.etag":"","ItemInternalId":"165bdb28-a541-4907-bf81-f5e47bc6d6d6","Año":"2026","Mes":"3","Unidad":"Proyecto Ariel","ALTAS":"0","BAJAS":"0","HC inicial":"0","HC final":"0","HC promedio":"0"},{"@odata.etag":"","ItemInternalId":"5a67c8ff-700f-46f7-a6d6-6a6cae496f00","Año":"2026","Mes":"4","Unidad":"Minera Casma","ALTAS":"52","BAJAS":"31","HC inicial":"527","HC final":"548","HC promedio":"537.5"},{"@odata.etag":"","ItemInternalId":"231cdbee-4d30-417f-8d58-4213b7e758bc","Año":"2026","Mes":"4","Unidad":"Sede Mina","ALTAS":"8","BAJAS":"3","HC inicial":"88","HC final":"93","HC promedio":"90.5"},{"@odata.etag":"","ItemInternalId":"dd6deafc-45a2-4d02-93fb-4cef15f1aef3","Año":"2026","Mes":"4","Unidad":"Planta Beneficio","ALTAS":"10","BAJAS":"6","HC inicial":"181","HC final":"185","HC promedio":"183"},{"@odata.etag":"","ItemInternalId":"91b09132-c6e8-471b-a142-cc10954ccc98","Año":"2026","Mes":"4","Unidad":"Minera Onoaga","ALTAS":"25","BAJAS":"1","HC inicial":"75","HC final":"99","HC promedio":"87"},{"@odata.etag":"","ItemInternalId":"3792ad6b-3381-4263-8eb1-22fc9a72fa11","Año":"2026","Mes":"4","Unidad":"Proyecto Puno","ALTAS":"6","BAJAS":"0","HC inicial":"5","HC final":"11","HC promedio":"8"},{"@odata.etag":"","ItemInternalId":"f2849982-c95d-4840-a076-594f4543223b","Año":"2026","Mes":"4","Unidad":"Proyecto Ariel","ALTAS":"0","BAJAS":"0","HC inicial":"0","HC final":"","HC promedio":"0"}],"salidas_tiempo":[{"@odata.etag":"","ItemInternalId":"3c973b7e-2e28-473f-8ccd-31267a09a5dc","Año":"2025","Mes":"1","Unidad":"Minera Casma","MENOR A 3 MESES":"6","MENOR A 6 MESES":"7","MENOR A 4 AÑOS":"3","MENOR A 2 AÑOS":"0","MENOR A 3 AÑOS":"0","MENOR A 1 AÑO":"6","MENOR A 5 AÑOS":"0"},{"@odata.etag":"","ItemInternalId":"08b150d3-d948-4189-bc85-790e77e0917e","Año":"2025","Mes":"1","Unidad":"Sede Mina","MENOR A 3 MESES":"2","MENOR A 6 MESES":"2","MENOR A 4 AÑOS":"0","MENOR A 2 AÑOS":"2","MENOR A 3 AÑOS":"3","MENOR A 1 AÑO":"1","MENOR A 5 AÑOS":"0"},{"@odata.etag":"","ItemInternalId":"11ebd3ab-b1da-4d03-bc10-15fb276d1a80","Año":"2025","Mes":"1","Unidad":"Planta Beneficio","MENOR A 3 MESES":"3","MENOR A 6 MESES":"7","MENOR A 4 AÑOS":"3","MENOR A 2 AÑOS":"0","MENOR A 3 AÑOS":"2","MENOR A 1 AÑO":"1","MENOR A 5 AÑOS":"0"},{"@odata.etag":"","ItemInternalId":"d86a5e11-ffad-4b11-80ab-715f8db15b75","Año":"2025","Mes":"1","Unidad":"Minera Onoaga","MENOR A 3 MESES":"3","MENOR A 6 MESES":"2","MENOR A 4 AÑOS":"0","MENOR A 2 AÑOS":"0","MENOR A 3 AÑOS":"0","MENOR A 1 AÑO":"0","MENOR A 5 AÑOS":"0"},{"@odata.etag":"","ItemInternalId":"008054a4-5c29-47d9-a6e6-894a43da292a","Año":"2025","Mes":"1","Unidad":"Proyecto Puno","MENOR A 3 MESES":"0","MENOR A 6 MESES":"0","MENOR A 4 AÑOS":"0","MENOR A 2 AÑOS":"0","MENOR A 3 AÑOS":"0","MENOR A 1 AÑO":"0","MENOR A 5 AÑOS":"0"},{"@odata.etag":"","ItemInternalId":"a61c5506-84a6-49c1-94b8-8979d02acdaa","Año":"2025","Mes":"1","Unidad":"Proyecto Ariel","MENOR A 3 MESES":"0","MENOR A 6 MESES":"0","MENOR A 4 AÑOS":"0","MENOR A 2 AÑOS":"0","MENOR A 3 AÑOS":"0","MENOR A 1 AÑO":"0","MENOR A 5 AÑOS":"0"},{"@odata.etag":"","ItemInternalId":"2892b725-0ffa-444c-9a69-0281103856cb","Año":"2025","Mes":"2","Unidad":"Minera Casma","MENOR A 3 MESES":"5","MENOR A 6 MESES":"5","MENOR A 4 AÑOS":"13","MENOR A 2 AÑOS":"1","MENOR A 3 AÑOS":"3","MENOR A 1 AÑO":"5","MENOR A 5 AÑOS":"0"},{"@odata.etag":"","ItemInternalId":"84d0261e-c1cd-4625-8965-e1801ce58be1","Año":"2025","Mes":"2","Unidad":"Sede Mina","MENOR A 3 MESES":"0","MENOR A 6 MESES":"1","MENOR A 4 AÑOS":"1","MENOR A 2 AÑOS":"0","MENOR A 3 AÑOS":"1","MENOR A 1 AÑO":"1","MENOR A 5 AÑOS":"0"},{"@odata.etag":"","ItemInternalId":"61272eee-7f73-4256-8aaa-e7c03c55ddeb","Año":"2025","Mes":"2","Unidad":"Planta Beneficio","MENOR A 3 MESES":"1","MENOR A 6 MESES":"1","MENOR A 4 AÑOS":"2","MENOR A 2 AÑOS":"0","MENOR A 3 AÑOS":"0","MENOR A 1 AÑO":"2","MENOR A 5 AÑOS":"0"},{"@odata.etag":"","ItemInternalId":"4fbd456a-f6d7-4743-a57d-64efbed3fa8d","Año":"2025","Mes":"2","Unidad":"Minera Onoaga","MENOR A 3 MESES":"0","MENOR A 6 MESES":"1","MENOR A 4 AÑOS":"0","MENOR A 2 AÑOS":"0","MENOR A 3 AÑOS":"1","MENOR A 1 AÑO":"1","MENOR A 5 AÑOS":"0"},{"@odata.etag":"","ItemInternalId":"21a2e2f6-8522-482a-9205-7b9ee3dd8de1","Año":"2025","Mes":"2","Unidad":"Proyecto Puno","MENOR A 3 MESES":"0","MENOR A 6 MESES":"0","MENOR A 4 AÑOS":"0","MENOR A 2 AÑOS":"0","MENOR A 3 AÑOS":"0","MENOR A 1 AÑO":"0","MENOR A 5 AÑOS":"0"},{"@odata.etag":"","ItemInternalId":"d6b2d014-1d6d-4f4e-ae89-0febfff37e9f","Año":"2025","Mes":"2","Unidad":"Proyecto Ariel","MENOR A 3 MESES":"0","MENOR A 6 MESES":"0","MENOR A 4 AÑOS":"0","MENOR A 2 AÑOS":"0","MENOR A 3 AÑOS":"0","MENOR A 1 AÑO":"0","MENOR A 5 AÑOS":"0"},{"@odata.etag":"","ItemInternalId":"712c449a-b835-4943-b0e2-44e3fb9b0440","Año":"2025","Mes":"3","Unidad":"Minera Casma","MENOR A 3 MESES":"13","MENOR A 6 MESES":"3","MENOR A 4 AÑOS":"3","MENOR A 2 AÑOS":"2","MENOR A 3 AÑOS":"3","MENOR A 1 AÑO":"6","MENOR A 5 AÑOS":"0"},{"@odata.etag":"","ItemInternalId":"083e9dae-a422-4ce8-8e3f-509523893ac6","Año":"2025","Mes":"3","Unidad":"Sede Mina","MENOR A 3 MESES":"2","MENOR A 6 MESES":"0","MENOR A 4 AÑOS":"0","MENOR A 2 AÑOS":"2","MENOR A 3 AÑOS":"1","MENOR A 1 AÑO":"5","MENOR A 5 AÑOS":"0"},{"@odata.etag":"","ItemInternalId":"8bda731f-8942-4327-ad08-f59a7fa0e42b","Año":"2025","Mes":"3","Unidad":"Planta Beneficio","MENOR A 3 MESES":"2","MENOR A 6 MESES":"2","MENOR A 4 AÑOS":"0","MENOR A 2 AÑOS":"0","MENOR A 3 AÑOS":"2","MENOR A 1 AÑO":"0","MENOR A 5 AÑOS":"0"},{"@odata.etag":"","ItemInternalId":"58bde093-332b-4b1f-8230-18067bed4ed5","Año":"2025","Mes":"3","Unidad":"Minera Onoaga","MENOR A 3 MESES":"2","MENOR A 6 MESES":"1","MENOR A 4 AÑOS":"0","MENOR A 2 AÑOS":"0","MENOR A 3 AÑOS":"0","MENOR A 1 AÑO":"1","MENOR A 5 AÑOS":"0"},{"@odata.etag":"","ItemInternalId":"b4357632-cb7b-4020-9580-67d68bea231e","Año":"2025","Mes":"3","Unidad":"Proyecto Puno","MENOR A 3 MESES":"0","MENOR A 6 MESES":"0","MENOR A 4 AÑOS":"0","MENOR A 2 AÑOS":"0","MENOR A 3 AÑOS":"0","MENOR A 1 AÑO":"0","MENOR A 5 AÑOS":"0"},{"@odata.etag":"","ItemInternalId":"2aa88982-e16c-4e8f-b59e-bf85c8c76a24","Año":"2025","Mes":"3","Unidad":"Proyecto Ariel","MENOR A 3 MESES":"0","MENOR A 6 MESES":"0","MENOR A 4 AÑOS":"0","MENOR A 2 AÑOS":"0","MENOR A 3 AÑOS":"0","MENOR A 1 AÑO":"0","MENOR A 5 AÑOS":"0"},{"@odata.etag":"","ItemInternalId":"0f697a0e-72c0-4d89-a50a-4013cde0bc50","Año":"2025","Mes":"4","Unidad":"Minera Casma","MENOR A 3 MESES":"17","MENOR A 6 MESES":"5","MENOR A 4 AÑOS":"2","MENOR A 2 AÑOS":"1","MENOR A 3 AÑOS":"2","MENOR A 1 AÑO":"2","MENOR A 5 AÑOS":"0"},{"@odata.etag":"","ItemInternalId":"6fbb4274-0bcd-48a9-9de6-9da771c5cc88","Año":"2025","Mes":"4","Unidad":"Sede Mina","MENOR A 3 MESES":"5","MENOR A 6 MESES":"0","MENOR A 4 AÑOS":"0","MENOR A 2 AÑOS":"0","MENOR A 3 AÑOS":"0","MENOR A 1 AÑO":"0","MENOR A 5 AÑOS":"0"},{"@odata.etag":"","ItemInternalId":"214609a7-6249-4665-9791-2765bbde10ca","Año":"2025","Mes":"4","Unidad":"Planta Beneficio","MENOR A 3 MESES":"1","MENOR A 6 MESES":"0","MENOR A 4 AÑOS":"0","MENOR A 2 AÑOS":"1","MENOR A 3 AÑOS":"1","MENOR A 1 AÑO":"2","MENOR A 5 AÑOS":"0"},{"@odata.etag":"","ItemInternalId":"3389ac49-20b5-4fda-9296-61a64cae47e3","Año":"2025","Mes":"4","Unidad":"Minera Onoaga","MENOR A 3 MESES":"2","MENOR A 6 MESES":"3","MENOR A 4 AÑOS":"0","MENOR A 2 AÑOS":"0","MENOR A 3 AÑOS":"0","MENOR A 1 AÑO":"0","MENOR A 5 AÑOS":"0"},{"@odata.etag":"","ItemInternalId":"e35b3558-c591-41fc-9028-065dfd64fb86","Año":"2025","Mes":"4","Unidad":"Proyecto Puno","MENOR A 3 MESES":"0","MENOR A 6 MESES":"0","MENOR A 4 AÑOS":"0","MENOR A 2 AÑOS":"0","MENOR A 3 AÑOS":"0","MENOR A 1 AÑO":"0","MENOR A 5 AÑOS":"0"},{"@odata.etag":"","ItemInternalId":"5bec4461-5ce1-4083-b8d5-de521fae13fa","Año":"2025","Mes":"4","Unidad":"Proyecto Ariel","MENOR A 3 MESES":"0","MENOR A 6 MESES":"0","MENOR A 4 AÑOS":"0","MENOR A 2 AÑOS":"0","MENOR A 3 AÑOS":"0","MENOR A 1 AÑO":"0","MENOR A 5 AÑOS":"0"},{"@odata.etag":"","ItemInternalId":"db7e9b24-72a4-484f-86a5-0fd989b7ec48","Año":"2025","Mes":"5","Unidad":"Minera Casma","MENOR A 3 MESES":"16","MENOR A 6 MESES":"8","MENOR A 4 AÑOS":"0","MENOR A 2 AÑOS":"2","MENOR A 3 AÑOS":"3","MENOR A 1 AÑO":"5","MENOR A 5 AÑOS":"0"},{"@odata.etag":"","ItemInternalId":"cc002266-6500-4ae8-9b84-ee2159e8aa97","Año":"2025","Mes":"5","Unidad":"Sede Mina","MENOR A 3 MESES":"0","MENOR A 6 MESES":"3","MENOR A 4 AÑOS":"0","MENOR A 2 AÑOS":"3","MENOR A 3 AÑOS":"2","MENOR A 1 AÑO":"1","MENOR A 5 AÑOS":"0"},{"@odata.etag":"","ItemInternalId":"8ab62578-e61a-445b-9a7e-c4accbef4750","Año":"2025","Mes":"5","Unidad":"Planta Beneficio","MENOR A 3 MESES":"2","MENOR A 6 MESES":"4","MENOR A 4 AÑOS":"0","MENOR A 2 AÑOS":"1","MENOR A 3 AÑOS":"0","MENOR A 1 AÑO":"3","MENOR A 5 AÑOS":"0"},{"@odata.etag":"","ItemInternalId":"19b73fc3-8d38-4589-80dd-443f2a08037a","Año":"2025","Mes":"5","Unidad":"Minera Onoaga","MENOR A 3 MESES":"0","MENOR A 6 MESES":"0","MENOR A 4 AÑOS":"0","MENOR A 2 AÑOS":"0","MENOR A 3 AÑOS":"0","MENOR A 1 AÑO":"2","MENOR A 5 AÑOS":"0"},{"@odata.etag":"","ItemInternalId":"f6de744a-2390-4044-949a-1838513b9e71","Año":"2025","Mes":"5","Unidad":"Proyecto Puno","MENOR A 3 MESES":"0","MENOR A 6 MESES":"0","MENOR A 4 AÑOS":"0","MENOR A 2 AÑOS":"0","MENOR A 3 AÑOS":"0","MENOR A 1 AÑO":"0","MENOR A 5 AÑOS":"0"},{"@odata.etag":"","ItemInternalId":"1269107b-6c4e-44f1-ba85-865ab5a128bd","Año":"2025","Mes":"5","Unidad":"Proyecto Ariel","MENOR A 3 MESES":"0","MENOR A 6 MESES":"0","MENOR A 4 AÑOS":"0","MENOR A 2 AÑOS":"0","MENOR A 3 AÑOS":"0","MENOR A 1 AÑO":"0","MENOR A 5 AÑOS":"0"},{"@odata.etag":"","ItemInternalId":"5e935cf0-848d-4559-88be-9774f539c5f7","Año":"2025","Mes":"6","Unidad":"Minera Casma","MENOR A 3 MESES":"4","MENOR A 6 MESES":"10","MENOR A 4 AÑOS":"0","MENOR A 2 AÑOS":"2","MENOR A 3 AÑOS":"0","MENOR A 1 AÑO":"1","MENOR A 5 AÑOS":"0"},{"@odata.etag":"","ItemInternalId":"af5a11e1-6f41-4ed5-8dd0-089cc15afebe","Año":"2025","Mes":"6","Unidad":"Sede Mina","MENOR A 3 MESES":"2","MENOR A 6 MESES":"0","MENOR A 4 AÑOS":"0","MENOR A 2 AÑOS":"1","MENOR A 3 AÑOS":"0","MENOR A 1 AÑO":"0","MENOR A 5 AÑOS":"0"},{"@odata.etag":"","ItemInternalId":"18c7b534-84a0-4aa3-8d00-1229a2c2248f","Año":"2025","Mes":"6","Unidad":"Planta Beneficio","MENOR A 3 MESES":"1","MENOR A 6 MESES":"2","MENOR A 4 AÑOS":"0","MENOR A 2 AÑOS":"0","MENOR A 3 AÑOS":"1","MENOR A 1 AÑO":"2","MENOR A 5 AÑOS":"0"},{"@odata.etag":"","ItemInternalId":"da40d24e-b772-48f4-9f20-8b4f1a03653e","Año":"2025","Mes":"6","Unidad":"Minera Onoaga","MENOR A 3 MESES":"0","MENOR A 6 MESES":"0","MENOR A 4 AÑOS":"0","MENOR A 2 AÑOS":"0","MENOR A 3 AÑOS":"0","MENOR A 1 AÑO":"0","MENOR A 5 AÑOS":"0"},{"@odata.etag":"","ItemInternalId":"a29769a1-3f8a-4829-b0e4-f5cc6dbf969e","Año":"2025","Mes":"6","Unidad":"Proyecto Puno","MENOR A 3 MESES":"0","MENOR A 6 MESES":"0","MENOR A 4 AÑOS":"0","MENOR A 2 AÑOS":"0","MENOR A 3 AÑOS":"0","MENOR A 1 AÑO":"0","MENOR A 5 AÑOS":"0"},{"@odata.etag":"","ItemInternalId":"89ee98d7-0c33-4493-be31-3d5e01c56a13","Año":"2025","Mes":"6","Unidad":"Proyecto Ariel","MENOR A 3 MESES":"0","MENOR A 6 MESES":"0","MENOR A 4 AÑOS":"0","MENOR A 2 AÑOS":"0","MENOR A 3 AÑOS":"0","MENOR A 1 AÑO":"0","MENOR A 5 AÑOS":"0"},{"@odata.etag":"","ItemInternalId":"67ff5a60-6d0c-4b85-8e33-ac7d5750ef17","Año":"2025","Mes":"7","Unidad":"Minera Casma","MENOR A 3 MESES":"11","MENOR A 6 MESES":"10","MENOR A 4 AÑOS":"0","MENOR A 2 AÑOS":"2","MENOR A 3 AÑOS":"3","MENOR A 1 AÑO":"12","MENOR A 5 AÑOS":"0"},{"@odata.etag":"","ItemInternalId":"ed030cb8-92cf-45be-b040-cad855bfaff9","Año":"2025","Mes":"7","Unidad":"Sede Mina","MENOR A 3 MESES":"2","MENOR A 6 MESES":"0","MENOR A 4 AÑOS":"0","MENOR A 2 AÑOS":"0","MENOR A 3 AÑOS":"0","MENOR A 1 AÑO":"0","MENOR A 5 AÑOS":"0"},{"@odata.etag":"","ItemInternalId":"8b692d92-bd52-4785-ba84-6b69f840e7a6","Año":"2025","Mes":"7","Unidad":"Planta Beneficio","MENOR A 3 MESES":"3","MENOR A 6 MESES":"1","MENOR A 4 AÑOS":"0","MENOR A 2 AÑOS":"1","MENOR A 3 AÑOS":"1","MENOR A 1 AÑO":"2","MENOR A 5 AÑOS":"0"},{"@odata.etag":"","ItemInternalId":"673b1ce3-75d0-4d9a-8911-d319e161057b","Año":"2025","Mes":"7","Unidad":"Minera Onoaga","MENOR A 3 MESES":"1","MENOR A 6 MESES":"1","MENOR A 4 AÑOS":"0","MENOR A 2 AÑOS":"0","MENOR A 3 AÑOS":"0","MENOR A 1 AÑO":"1","MENOR A 5 AÑOS":"0"},{"@odata.etag":"","ItemInternalId":"71923048-8a93-41c9-bfa6-644e0ca9ce88","Año":"2025","Mes":"7","Unidad":"Proyecto Puno","MENOR A 3 MESES":"0","MENOR A 6 MESES":"0","MENOR A 4 AÑOS":"0","MENOR A 2 AÑOS":"0","MENOR A 3 AÑOS":"0","MENOR A 1 AÑO":"0","MENOR A 5 AÑOS":"0"},{"@odata.etag":"","ItemInternalId":"a64cf641-cc9b-4689-9875-29a101a7d8b3","Año":"2025","Mes":"7","Unidad":"Proyecto Ariel","MENOR A 3 MESES":"0","MENOR A 6 MESES":"0","MENOR A 4 AÑOS":"0","MENOR A 2 AÑOS":"0","MENOR A 3 AÑOS":"0","MENOR A 1 AÑO":"0","MENOR A 5 AÑOS":"0"},{"@odata.etag":"","ItemInternalId":"e8c0f051-b85b-43fa-b0f2-e03d74ccd01e","Año":"2025","Mes":"8","Unidad":"Minera Casma","MENOR A 3 MESES":"22","MENOR A 6 MESES":"10","MENOR A 4 AÑOS":"0","MENOR A 2 AÑOS":"3","MENOR A 3 AÑOS":"1","MENOR A 1 AÑO":"8","MENOR A 5 AÑOS":"0"},{"@odata.etag":"","ItemInternalId":"5702e9d6-a928-4ce8-bc43-19242eb7459f","Año":"2025","Mes":"8","Unidad":"Sede Mina","MENOR A 3 MESES":"1","MENOR A 6 MESES":"2","MENOR A 4 AÑOS":"0","MENOR A 2 AÑOS":"1","MENOR A 3 AÑOS":"0","MENOR A 1 AÑO":"0","MENOR A 5 AÑOS":"0"},{"@odata.etag":"","ItemInternalId":"d0a20127-8bd4-46d2-bad2-b38814cce318","Año":"2025","Mes":"8","Unidad":"Planta Beneficio","MENOR A 3 MESES":"1","MENOR A 6 MESES":"0","MENOR A 4 AÑOS":"1","MENOR A 2 AÑOS":"2","MENOR A 3 AÑOS":"5","MENOR A 1 AÑO":"2","MENOR A 5 AÑOS":"0"},{"@odata.etag":"","ItemInternalId":"36681a25-2f0f-4bca-b3a9-6dfae687a7c2","Año":"2025","Mes":"8","Unidad":"Minera Onoaga","MENOR A 3 MESES":"1","MENOR A 6 MESES":"2","MENOR A 4 AÑOS":"0","MENOR A 2 AÑOS":"3","MENOR A 3 AÑOS":"0","MENOR A 1 AÑO":"0","MENOR A 5 AÑOS":"0"},{"@odata.etag":"","ItemInternalId":"2325036f-9da1-4661-a7d1-582c836a3042","Año":"2025","Mes":"8","Unidad":"Proyecto Puno","MENOR A 3 MESES":"0","MENOR A 6 MESES":"1","MENOR A 4 AÑOS":"0","MENOR A 2 AÑOS":"0","MENOR A 3 AÑOS":"0","MENOR A 1 AÑO":"0","MENOR A 5 AÑOS":"0"},{"@odata.etag":"","ItemInternalId":"dc62a71f-2faa-486a-bc2f-2d03c741aa9f","Año":"2025","Mes":"8","Unidad":"Proyecto Ariel","MENOR A 3 MESES":"0","MENOR A 6 MESES":"0","MENOR A 4 AÑOS":"0","MENOR A 2 AÑOS":"0","MENOR A 3 AÑOS":"0","MENOR A 1 AÑO":"0","MENOR A 5 AÑOS":"0"},{"@odata.etag":"","ItemInternalId":"fa8187e6-85be-43e9-9c88-2cead555c6b7","Año":"2025","Mes":"9","Unidad":"Minera Casma","MENOR A 3 MESES":"12","MENOR A 6 MESES":"8","MENOR A 4 AÑOS":"0","MENOR A 2 AÑOS":"2","MENOR A 3 AÑOS":"1","MENOR A 1 AÑO":"4","MENOR A 5 AÑOS":"0"},{"@odata.etag":"","ItemInternalId":"a7deb567-648b-4176-b197-1a78bcc75f57","Año":"2025","Mes":"9","Unidad":"Sede Mina","MENOR A 3 MESES":"1","MENOR A 6 MESES":"2","MENOR A 4 AÑOS":"0","MENOR A 2 AÑOS":"5","MENOR A 3 AÑOS":"2","MENOR A 1 AÑO":"2","MENOR A 5 AÑOS":"0"},{"@odata.etag":"","ItemInternalId":"b0ce1509-f45e-4c8c-936b-3bd843b07b25","Año":"2025","Mes":"9","Unidad":"Planta Beneficio","MENOR A 3 MESES":"0","MENOR A 6 MESES":"0","MENOR A 4 AÑOS":"0","MENOR A 2 AÑOS":"0","MENOR A 3 AÑOS":"0","MENOR A 1 AÑO":"0","MENOR A 5 AÑOS":"0"},{"@odata.etag":"","ItemInternalId":"5fcae5ad-df10-481f-ae0b-1ff5ea927670","Año":"2025","Mes":"9","Unidad":"Minera Onoaga","MENOR A 3 MESES":"1","MENOR A 6 MESES":"0","MENOR A 4 AÑOS":"0","MENOR A 2 AÑOS":"0","MENOR A 3 AÑOS":"0","MENOR A 1 AÑO":"2","MENOR A 5 AÑOS":"0"},{"@odata.etag":"","ItemInternalId":"72723313-9b09-462e-8878-d9316673dfc5","Año":"2025","Mes":"9","Unidad":"Proyecto Puno","MENOR A 3 MESES":"0","MENOR A 6 MESES":"0","MENOR A 4 AÑOS":"0","MENOR A 2 AÑOS":"0","MENOR A 3 AÑOS":"0","MENOR A 1 AÑO":"1","MENOR A 5 AÑOS":"0"},{"@odata.etag":"","ItemInternalId":"03a797e0-f89f-44cb-9111-d7d1f2710cd0","Año":"2025","Mes":"9","Unidad":"Proyecto Ariel","MENOR A 3 MESES":"0","MENOR A 6 MESES":"0","MENOR A 4 AÑOS":"0","MENOR A 2 AÑOS":"0","MENOR A 3 AÑOS":"0","MENOR A 1 AÑO":"0","MENOR A 5 AÑOS":"0"},{"@odata.etag":"","ItemInternalId":"54554350-c567-4d89-b5f4-7eb5371e622b","Año":"2025","Mes":"10","Unidad":"Minera Casma","MENOR A 3 MESES":"11","MENOR A 6 MESES":"8","MENOR A 4 AÑOS":"3","MENOR A 2 AÑOS":"6","MENOR A 3 AÑOS":"2","MENOR A 1 AÑO":"14","MENOR A 5 AÑOS":"0"},{"@odata.etag":"","ItemInternalId":"e21fb249-4a9c-4780-adba-835ad39fd589","Año":"2025","Mes":"10","Unidad":"Sede Mina","MENOR A 3 MESES":"3","MENOR A 6 MESES":"0","MENOR A 4 AÑOS":"0","MENOR A 2 AÑOS":"0","MENOR A 3 AÑOS":"0","MENOR A 1 AÑO":"1","MENOR A 5 AÑOS":"0"},{"@odata.etag":"","ItemInternalId":"c288364b-4089-43d7-b417-dbbfdafeaa65","Año":"2025","Mes":"10","Unidad":"Planta Beneficio","MENOR A 3 MESES":"0","MENOR A 6 MESES":"0","MENOR A 4 AÑOS":"3","MENOR A 2 AÑOS":"3","MENOR A 3 AÑOS":"2","MENOR A 1 AÑO":"1","MENOR A 5 AÑOS":"0"},{"@odata.etag":"","ItemInternalId":"ce543ebc-9cb9-4db0-8fc0-8cf21e352428","Año":"2025","Mes":"10","Unidad":"Minera Onoaga","MENOR A 3 MESES":"0","MENOR A 6 MESES":"1","MENOR A 4 AÑOS":"0","MENOR A 2 AÑOS":"1","MENOR A 3 AÑOS":"0","MENOR A 1 AÑO":"0","MENOR A 5 AÑOS":"0"},{"@odata.etag":"","ItemInternalId":"d2228390-f268-4be9-a3e3-d70541a3785e","Año":"2025","Mes":"10","Unidad":"Proyecto Puno","MENOR A 3 MESES":"0","MENOR A 6 MESES":"0","MENOR A 4 AÑOS":"0","MENOR A 2 AÑOS":"0","MENOR A 3 AÑOS":"0","MENOR A 1 AÑO":"0","MENOR A 5 AÑOS":"0"},{"@odata.etag":"","ItemInternalId":"a21406cd-b472-419f-80b7-ee1ef8486435","Año":"2025","Mes":"10","Unidad":"Proyecto Ariel","MENOR A 3 MESES":"0","MENOR A 6 MESES":"0","MENOR A 4 AÑOS":"0","MENOR A 2 AÑOS":"0","MENOR A 3 AÑOS":"0","MENOR A 1 AÑO":"0","MENOR A 5 AÑOS":"0"},{"@odata.etag":"","ItemInternalId":"08c85b34-f89a-468a-8bf6-7311c78a5e86","Año":"2025","Mes":"11","Unidad":"Minera Casma","MENOR A 3 MESES":"14","MENOR A 6 MESES":"8","MENOR A 4 AÑOS":"0","MENOR A 2 AÑOS":"7","MENOR A 3 AÑOS":"3","MENOR A 1 AÑO":"5","MENOR A 5 AÑOS":"0"},{"@odata.etag":"","ItemInternalId":"d91ed840-d37f-4825-aadc-0b310ff3b266","Año":"2025","Mes":"11","Unidad":"Sede Mina","MENOR A 3 MESES":"1","MENOR A 6 MESES":"0","MENOR A 4 AÑOS":"1","MENOR A 2 AÑOS":"0","MENOR A 3 AÑOS":"0","MENOR A 1 AÑO":"0","MENOR A 5 AÑOS":"0"},{"@odata.etag":"","ItemInternalId":"29fdc51c-65b0-4047-b264-97b4129a0c28","Año":"2025","Mes":"11","Unidad":"Planta Beneficio","MENOR A 3 MESES":"0","MENOR A 6 MESES":"1","MENOR A 4 AÑOS":"2","MENOR A 2 AÑOS":"2","MENOR A 3 AÑOS":"1","MENOR A 1 AÑO":"1","MENOR A 5 AÑOS":"0"},{"@odata.etag":"","ItemInternalId":"7fb6571e-8154-4ca4-bc82-8879583ffe09","Año":"2025","Mes":"11","Unidad":"Minera Onoaga","MENOR A 3 MESES":"2","MENOR A 6 MESES":"1","MENOR A 4 AÑOS":"0","MENOR A 2 AÑOS":"1","MENOR A 3 AÑOS":"0","MENOR A 1 AÑO":"2","MENOR A 5 AÑOS":"0"},{"@odata.etag":"","ItemInternalId":"2a1483b9-a958-4a1b-83d7-4036d6cf055b","Año":"2025","Mes":"11","Unidad":"Proyecto Puno","MENOR A 3 MESES":"0","MENOR A 6 MESES":"0","MENOR A 4 AÑOS":"0","MENOR A 2 AÑOS":"0","MENOR A 3 AÑOS":"0","MENOR A 1 AÑO":"0","MENOR A 5 AÑOS":"0"},{"@odata.etag":"","ItemInternalId":"716d67f2-dc69-42b6-84d9-c0c1d6ac11a0","Año":"2025","Mes":"11","Unidad":"Proyecto Ariel","MENOR A 3 MESES":"0","MENOR A 6 MESES":"0","MENOR A 4 AÑOS":"0","MENOR A 2 AÑOS":"0","MENOR A 3 AÑOS":"0","MENOR A 1 AÑO":"0","MENOR A 5 AÑOS":"0"},{"@odata.etag":"","ItemInternalId":"b108448c-52f9-4bd4-98b8-0c859a777313","Año":"2025","Mes":"12","Unidad":"Minera Casma","MENOR A 3 MESES":"13","MENOR A 6 MESES":"21","MENOR A 4 AÑOS":"0","MENOR A 2 AÑOS":"4","MENOR A 3 AÑOS":"1","MENOR A 1 AÑO":"22","MENOR A 5 AÑOS":"0"},{"@odata.etag":"","ItemInternalId":"1f8c377c-93da-48bc-bd75-7cd49a34bca7","Año":"2025","Mes":"12","Unidad":"Sede Mina","MENOR A 3 MESES":"6","MENOR A 6 MESES":"1","MENOR A 4 AÑOS":"0","MENOR A 2 AÑOS":"0","MENOR A 3 AÑOS":"0","MENOR A 1 AÑO":"2","MENOR A 5 AÑOS":"0"},{"@odata.etag":"","ItemInternalId":"b4321ab9-bc24-42fe-aba3-34a8f39e8e0c","Año":"2025","Mes":"12","Unidad":"Planta Beneficio","MENOR A 3 MESES":"0","MENOR A 6 MESES":"2","MENOR A 4 AÑOS":"0","MENOR A 2 AÑOS":"0","MENOR A 3 AÑOS":"1","MENOR A 1 AÑO":"0","MENOR A 5 AÑOS":"0"},{"@odata.etag":"","ItemInternalId":"87d4fb63-0793-443b-9b59-c11293a8fa1b","Año":"2025","Mes":"12","Unidad":"Minera Onoaga","MENOR A 3 MESES":"0","MENOR A 6 MESES":"2","MENOR A 4 AÑOS":"0","MENOR A 2 AÑOS":"0","MENOR A 3 AÑOS":"0","MENOR A 1 AÑO":"1","MENOR A 5 AÑOS":"0"},{"@odata.etag":"","ItemInternalId":"22e32db1-8d1c-4ff3-8372-f30d82a8d948","Año":"2025","Mes":"12","Unidad":"Proyecto Puno","MENOR A 3 MESES":"0","MENOR A 6 MESES":"0","MENOR A 4 AÑOS":"0","MENOR A 2 AÑOS":"0","MENOR A 3 AÑOS":"0","MENOR A 1 AÑO":"0","MENOR A 5 AÑOS":"0"},{"@odata.etag":"","ItemInternalId":"e0af5671-f3a4-4b22-bc8b-8da261250a1b","Año":"2025","Mes":"12","Unidad":"Proyecto Ariel","MENOR A 3 MESES":"0","MENOR A 6 MESES":"0","MENOR A 4 AÑOS":"0","MENOR A 2 AÑOS":"0","MENOR A 3 AÑOS":"0","MENOR A 1 AÑO":"0","MENOR A 5 AÑOS":"0"},{"@odata.etag":"","ItemInternalId":"d3b84e65-1638-47eb-9092-3c14e18b0d4f","Año":"2026","Mes":"1","Unidad":"Minera Casma","MENOR A 3 MESES":"9","MENOR A 6 MESES":"18","MENOR A 4 AÑOS":"3","MENOR A 2 AÑOS":"0","MENOR A 3 AÑOS":"5","MENOR A 1 AÑO":"8","MENOR A 5 AÑOS":"1"},{"@odata.etag":"","ItemInternalId":"0631e8fe-5289-4a2e-8e23-d4cd508f23ba","Año":"2026","Mes":"1","Unidad":"Sede Mina","MENOR A 3 MESES":"0","MENOR A 6 MESES":"2","MENOR A 4 AÑOS":"0","MENOR A 2 AÑOS":"0","MENOR A 3 AÑOS":"3","MENOR A 1 AÑO":"1","MENOR A 5 AÑOS":"0"},{"@odata.etag":"","ItemInternalId":"9312d5aa-9180-454a-ad28-f8f301aacf27","Año":"2026","Mes":"1","Unidad":"Planta Beneficio","MENOR A 3 MESES":"0","MENOR A 6 MESES":"1","MENOR A 4 AÑOS":"1","MENOR A 2 AÑOS":"2","MENOR A 3 AÑOS":"3","MENOR A 1 AÑO":"0","MENOR A 5 AÑOS":"0"},{"@odata.etag":"","ItemInternalId":"9a8f3e33-1325-48e6-acc0-c67404ec4a03","Año":"2026","Mes":"1","Unidad":"Minera Onoaga","MENOR A 3 MESES":"3","MENOR A 6 MESES":"1","MENOR A 4 AÑOS":"0","MENOR A 2 AÑOS":"0","MENOR A 3 AÑOS":"3","MENOR A 1 AÑO":"0","MENOR A 5 AÑOS":"0"},{"@odata.etag":"","ItemInternalId":"3f665379-c442-42e6-94ef-b679cc1de95d","Año":"2026","Mes":"1","Unidad":"Proyecto Puno","MENOR A 3 MESES":"0","MENOR A 6 MESES":"1","MENOR A 4 AÑOS":"0","MENOR A 2 AÑOS":"0","MENOR A 3 AÑOS":"0","MENOR A 1 AÑO":"0","MENOR A 5 AÑOS":"0"},{"@odata.etag":"","ItemInternalId":"d48804a9-30d3-4d9f-be02-ee2e31670c43","Año":"2026","Mes":"1","Unidad":"Proyecto Ariel","MENOR A 3 MESES":"0","MENOR A 6 MESES":"0","MENOR A 4 AÑOS":"0","MENOR A 2 AÑOS":"0","MENOR A 3 AÑOS":"0","MENOR A 1 AÑO":"0","MENOR A 5 AÑOS":"0"},{"@odata.etag":"","ItemInternalId":"fb9e14b0-a130-476b-8400-b669790adb39","Año":"2026","Mes":"2","Unidad":"Minera Casma","MENOR A 3 MESES":"15","MENOR A 6 MESES":"5","MENOR A 4 AÑOS":"2","MENOR A 2 AÑOS":"2","MENOR A 3 AÑOS":"3","MENOR A 1 AÑO":"4","MENOR A 5 AÑOS":"1"},{"@odata.etag":"","ItemInternalId":"17c98694-ae9c-44d9-a74d-56777ef1143d","Año":"2026","Mes":"2","Unidad":"Sede Mina","MENOR A 3 MESES":"2","MENOR A 6 MESES":"1","MENOR A 4 AÑOS":"0","MENOR A 2 AÑOS":"0","MENOR A 3 AÑOS":"0","MENOR A 1 AÑO":"0","MENOR A 5 AÑOS":"0"},{"@odata.etag":"","ItemInternalId":"fa73e2db-ff46-45b3-88d3-021683c2bc13","Año":"2026","Mes":"2","Unidad":"Planta Beneficio","MENOR A 3 MESES":"1","MENOR A 6 MESES":"1","MENOR A 4 AÑOS":"2","MENOR A 2 AÑOS":"3","MENOR A 3 AÑOS":"2","MENOR A 1 AÑO":"0","MENOR A 5 AÑOS":"0"},{"@odata.etag":"","ItemInternalId":"b72b6ef7-942c-4540-857b-613a2f72c1b0","Año":"2026","Mes":"2","Unidad":"Minera Onoaga","MENOR A 3 MESES":"2","MENOR A 6 MESES":"2","MENOR A 4 AÑOS":"0","MENOR A 2 AÑOS":"0","MENOR A 3 AÑOS":"1","MENOR A 1 AÑO":"2","MENOR A 5 AÑOS":"0"},{"@odata.etag":"","ItemInternalId":"28754c23-92bf-4cda-a40f-7cdf3e48557f","Año":"2026","Mes":"2","Unidad":"Proyecto Puno","MENOR A 3 MESES":"0","MENOR A 6 MESES":"0","MENOR A 4 AÑOS":"0","MENOR A 2 AÑOS":"0","MENOR A 3 AÑOS":"0","MENOR A 1 AÑO":"0","MENOR A 5 AÑOS":"0"},{"@odata.etag":"","ItemInternalId":"76cf4461-c5f2-4bce-9294-51a11c4030a7","Año":"2026","Mes":"2","Unidad":"Proyecto Ariel","MENOR A 3 MESES":"0","MENOR A 6 MESES":"0","MENOR A 4 AÑOS":"0","MENOR A 2 AÑOS":"0","MENOR A 3 AÑOS":"0","MENOR A 1 AÑO":"0","MENOR A 5 AÑOS":"0"},{"@odata.etag":"","ItemInternalId":"998bef3e-ac39-4c49-8cc7-0e1ddf91ae6f","Año":"2026","Mes":"3","Unidad":"Minera Casma","MENOR A 3 MESES":"22","MENOR A 6 MESES":"4","MENOR A 4 AÑOS":"2","MENOR A 2 AÑOS":"2","MENOR A 3 AÑOS":"5","MENOR A 1 AÑO":"8","MENOR A 5 AÑOS":"0"},{"@odata.etag":"","ItemInternalId":"4898c6b8-5029-4542-934c-da01954a9a04","Año":"2026","Mes":"3","Unidad":"Sede Mina","MENOR A 3 MESES":"2","MENOR A 6 MESES":"0","MENOR A 4 AÑOS":"0","MENOR A 2 AÑOS":"0","MENOR A 3 AÑOS":"0","MENOR A 1 AÑO":"1","MENOR A 5 AÑOS":"0"},{"@odata.etag":"","ItemInternalId":"8dc06aca-d28c-4d69-a766-ff1cf43cffcc","Año":"2026","Mes":"3","Unidad":"Planta Beneficio","MENOR A 3 MESES":"3","MENOR A 6 MESES":"0","MENOR A 4 AÑOS":"1","MENOR A 2 AÑOS":"2","MENOR A 3 AÑOS":"2","MENOR A 1 AÑO":"0","MENOR A 5 AÑOS":"0"},{"@odata.etag":"","ItemInternalId":"2bd4332d-4d19-459b-8c0b-2a65967791d7","Año":"2026","Mes":"3","Unidad":"Minera Onoaga","MENOR A 3 MESES":"4","MENOR A 6 MESES":"3","MENOR A 4 AÑOS":"0","MENOR A 2 AÑOS":"0","MENOR A 3 AÑOS":"1","MENOR A 1 AÑO":"2","MENOR A 5 AÑOS":"0"},{"@odata.etag":"","ItemInternalId":"8627d0e9-1306-4439-a381-e05a8292079e","Año":"2026","Mes":"3","Unidad":"Proyecto Puno","MENOR A 3 MESES":"0","MENOR A 6 MESES":"0","MENOR A 4 AÑOS":"0","MENOR A 2 AÑOS":"0","MENOR A 3 AÑOS":"0","MENOR A 1 AÑO":"0","MENOR A 5 AÑOS":"0"},{"@odata.etag":"","ItemInternalId":"d9f305f5-d6ec-466c-af3e-8467bf8afabc","Año":"2026","Mes":"3","Unidad":"Proyecto Ariel","MENOR A 3 MESES":"0","MENOR A 6 MESES":"0","MENOR A 4 AÑOS":"0","MENOR A 2 AÑOS":"0","MENOR A 3 AÑOS":"0","MENOR A 1 AÑO":"0","MENOR A 5 AÑOS":"0"},{"@odata.etag":"","ItemInternalId":"19fb3d89-0cca-4bb3-8786-457c92adec05","Año":"2026","Mes":"4","Unidad":"Minera Casma","MENOR A 3 MESES":"19","MENOR A 6 MESES":"9","MENOR A 4 AÑOS":"0","MENOR A 2 AÑOS":"0","MENOR A 3 AÑOS":"0","MENOR A 1 AÑO":"3","MENOR A 5 AÑOS":"0"},{"@odata.etag":"","ItemInternalId":"d4f7634b-a99f-48fd-9b18-7faeec2ec20c","Año":"2026","Mes":"4","Unidad":"Sede Mina","MENOR A 3 MESES":"1","MENOR A 6 MESES":"0","MENOR A 4 AÑOS":"0","MENOR A 2 AÑOS":"0","MENOR A 3 AÑOS":"0","MENOR A 1 AÑO":"2","MENOR A 5 AÑOS":"0"},{"@odata.etag":"","ItemInternalId":"d6da701e-0c67-4f29-820c-509ce4805eb7","Año":"2026","Mes":"4","Unidad":"Planta Beneficio","MENOR A 3 MESES":"0","MENOR A 6 MESES":"1","MENOR A 4 AÑOS":"1","MENOR A 2 AÑOS":"2","MENOR A 3 AÑOS":"1","MENOR A 1 AÑO":"1","MENOR A 5 AÑOS":"0"},{"@odata.etag":"","ItemInternalId":"c5506596-653d-43b3-852c-8eec188ba16b","Año":"2026","Mes":"4","Unidad":"Minera Onoaga","MENOR A 3 MESES":"0","MENOR A 6 MESES":"1","MENOR A 4 AÑOS":"0","MENOR A 2 AÑOS":"0","MENOR A 3 AÑOS":"0","MENOR A 1 AÑO":"0","MENOR A 5 AÑOS":"0"},{"@odata.etag":"","ItemInternalId":"1a7b747b-eece-4b55-9ca6-adf64c8eb804","Año":"2026","Mes":"4","Unidad":"Proyecto Puno","MENOR A 3 MESES":"0","MENOR A 6 MESES":"0","MENOR A 4 AÑOS":"0","MENOR A 2 AÑOS":"0","MENOR A 3 AÑOS":"0","MENOR A 1 AÑO":"0","MENOR A 5 AÑOS":"0"},{"@odata.etag":"","ItemInternalId":"30a5c80d-5186-4556-9662-3169befb3baa","Año":"2026","Mes":"4","Unidad":"Proyecto Ariel","MENOR A 3 MESES":"0","MENOR A 6 MESES":"0","MENOR A 4 AÑOS":"0","MENOR A 2 AÑOS":"0","MENOR A 3 AÑOS":"0","MENOR A 1 AÑO":"0","MENOR A 5 AÑOS":"0"}],"salidas_motivo":[{"@odata.etag":"","ItemInternalId":"65d3441c-807c-4df6-b217-26fd7d033859","Año":"2025","Mes":"1","Unidad":"Minera Casma","RENUNCIA":"13","TERMINACIÓN DE LA OBRA O SERVICIO, O VENCIMIENTO DEL PLAZO":"1","CRS":"4","FALLECIMIENTO":"0","DESPIDO O DESTITUCIÓN (Sin Indemnización)":"4","DESPIDO EN PERIODO DE PRUEBA":"0","NO RENOVACION":"0","ANULACION DE INGRESO":"0"},{"@odata.etag":"","ItemInternalId":"07280bfe-bf0f-4104-93ff-07f3cdc21423","Año":"2025","Mes":"1","Unidad":"Sede Mina","RENUNCIA":"7","TERMINACIÓN DE LA OBRA O SERVICIO, O VENCIMIENTO DEL PLAZO":"3","CRS":"0","FALLECIMIENTO":"0","DESPIDO O DESTITUCIÓN (Sin Indemnización)":"0","DESPIDO EN PERIODO DE PRUEBA":"0","NO RENOVACION":"0","ANULACION DE INGRESO":"0"},{"@odata.etag":"","ItemInternalId":"346e6bf8-1023-4d34-b0db-66ddf79d2327","Año":"2025","Mes":"1","Unidad":"Planta Beneficio","RENUNCIA":"6","TERMINACIÓN DE LA OBRA O SERVICIO, O VENCIMIENTO DEL PLAZO":"8","CRS":"1","FALLECIMIENTO":"0","DESPIDO O DESTITUCIÓN (Sin Indemnización)":"1","DESPIDO EN PERIODO DE PRUEBA":"0","NO RENOVACION":"0","ANULACION DE INGRESO":"0"},{"@odata.etag":"","ItemInternalId":"28b36542-fb0d-42ee-a485-63cef6e70285","Año":"2025","Mes":"1","Unidad":"Minera Onoaga","RENUNCIA":"5","TERMINACIÓN DE LA OBRA O SERVICIO, O VENCIMIENTO DEL PLAZO":"0","CRS":"0","FALLECIMIENTO":"0","DESPIDO O DESTITUCIÓN (Sin Indemnización)":"0","DESPIDO EN PERIODO DE PRUEBA":"0","NO RENOVACION":"0","ANULACION DE INGRESO":"0"},{"@odata.etag":"","ItemInternalId":"9faf2231-49b2-4e6e-92d8-b6d193abf04e","Año":"2025","Mes":"1","Unidad":"Proyecto Puno","RENUNCIA":"0","TERMINACIÓN DE LA OBRA O SERVICIO, O VENCIMIENTO DEL PLAZO":"0","CRS":"0","FALLECIMIENTO":"0","DESPIDO O DESTITUCIÓN (Sin Indemnización)":"0","DESPIDO EN PERIODO DE PRUEBA":"0","NO RENOVACION":"0","ANULACION DE INGRESO":"0"},{"@odata.etag":"","ItemInternalId":"8916eae9-f77f-42c3-b47b-8de45764892d","Año":"2025","Mes":"1","Unidad":"Proyecto Ariel","RENUNCIA":"0","TERMINACIÓN DE LA OBRA O SERVICIO, O VENCIMIENTO DEL PLAZO":"0","CRS":"0","FALLECIMIENTO":"0","DESPIDO O DESTITUCIÓN (Sin Indemnización)":"0","DESPIDO EN PERIODO DE PRUEBA":"0","NO RENOVACION":"0","ANULACION DE INGRESO":"0"},{"@odata.etag":"","ItemInternalId":"6a6ba27a-fe59-42b5-a24c-51da5049f424","Año":"2025","Mes":"2","Unidad":"Minera Casma","RENUNCIA":"16","TERMINACIÓN DE LA OBRA O SERVICIO, O VENCIMIENTO DEL PLAZO":"7","CRS":"9","FALLECIMIENTO":"0","DESPIDO O DESTITUCIÓN (Sin Indemnización)":"0","DESPIDO EN PERIODO DE PRUEBA":"0","NO RENOVACION":"0","ANULACION DE INGRESO":"0"},{"@odata.etag":"","ItemInternalId":"e4e34692-b231-43f7-87de-dc6a6454a7ef","Año":"2025","Mes":"2","Unidad":"Sede Mina","RENUNCIA":"3","TERMINACIÓN DE LA OBRA O SERVICIO, O VENCIMIENTO DEL PLAZO":"1","CRS":"0","FALLECIMIENTO":"0","DESPIDO O DESTITUCIÓN (Sin Indemnización)":"0","DESPIDO EN PERIODO DE PRUEBA":"0","NO RENOVACION":"0","ANULACION DE INGRESO":"0"},{"@odata.etag":"","ItemInternalId":"3b5e1dcb-8174-4caf-83f8-3e1d0fbebb02","Año":"2025","Mes":"2","Unidad":"Planta Beneficio","RENUNCIA":"0","TERMINACIÓN DE LA OBRA O SERVICIO, O VENCIMIENTO DEL PLAZO":"4","CRS":"2","FALLECIMIENTO":"0","DESPIDO O DESTITUCIÓN (Sin Indemnización)":"0","DESPIDO EN PERIODO DE PRUEBA":"0","NO RENOVACION":"0","ANULACION DE INGRESO":"0"},{"@odata.etag":"","ItemInternalId":"2ec63bc9-0b3c-4913-a0c7-2cba9281e79f","Año":"2025","Mes":"2","Unidad":"Minera Onoaga","RENUNCIA":"2","TERMINACIÓN DE LA OBRA O SERVICIO, O VENCIMIENTO DEL PLAZO":"0","CRS":"1","FALLECIMIENTO":"0","DESPIDO O DESTITUCIÓN (Sin Indemnización)":"0","DESPIDO EN PERIODO DE PRUEBA":"0","NO RENOVACION":"0","ANULACION DE INGRESO":"0"},{"@odata.etag":"","ItemInternalId":"1610730a-f18e-48aa-b359-36aa098d36a7","Año":"2025","Mes":"2","Unidad":"Proyecto Puno","RENUNCIA":"0","TERMINACIÓN DE LA OBRA O SERVICIO, O VENCIMIENTO DEL PLAZO":"0","CRS":"0","FALLECIMIENTO":"0","DESPIDO O DESTITUCIÓN (Sin Indemnización)":"0","DESPIDO EN PERIODO DE PRUEBA":"0","NO RENOVACION":"0","ANULACION DE INGRESO":"0"},{"@odata.etag":"","ItemInternalId":"a07a6226-f028-4599-81d9-8e5b3b1fb9ff","Año":"2025","Mes":"2","Unidad":"Proyecto Ariel","RENUNCIA":"0","TERMINACIÓN DE LA OBRA O SERVICIO, O VENCIMIENTO DEL PLAZO":"0","CRS":"0","FALLECIMIENTO":"0","DESPIDO O DESTITUCIÓN (Sin Indemnización)":"0","DESPIDO EN PERIODO DE PRUEBA":"0","NO RENOVACION":"0","ANULACION DE INGRESO":"0"},{"@odata.etag":"","ItemInternalId":"2d179e0e-b218-4c5c-8303-7e0df877fd32","Año":"2025","Mes":"3","Unidad":"Minera Casma","RENUNCIA":"25","TERMINACIÓN DE LA OBRA O SERVICIO, O VENCIMIENTO DEL PLAZO":"4","CRS":"0","FALLECIMIENTO":"0","DESPIDO O DESTITUCIÓN (Sin Indemnización)":"1","DESPIDO EN PERIODO DE PRUEBA":"0","NO RENOVACION":"0","ANULACION DE INGRESO":"0"},{"@odata.etag":"","ItemInternalId":"6ba5e3d1-2a49-4a28-8a3d-384a0e1976b0","Año":"2025","Mes":"3","Unidad":"Sede Mina","RENUNCIA":"10","TERMINACIÓN DE LA OBRA O SERVICIO, O VENCIMIENTO DEL PLAZO":"0","CRS":"0","FALLECIMIENTO":"0","DESPIDO O DESTITUCIÓN (Sin Indemnización)":"0","DESPIDO EN PERIODO DE PRUEBA":"0","NO RENOVACION":"0","ANULACION DE INGRESO":"0"},{"@odata.etag":"","ItemInternalId":"fad71466-83e2-449d-babb-9830b3a326dd","Año":"2025","Mes":"3","Unidad":"Planta Beneficio","RENUNCIA":"4","TERMINACIÓN DE LA OBRA O SERVICIO, O VENCIMIENTO DEL PLAZO":"0","CRS":"0","FALLECIMIENTO":"0","DESPIDO O DESTITUCIÓN (Sin Indemnización)":"2","DESPIDO EN PERIODO DE PRUEBA":"0","NO RENOVACION":"0","ANULACION DE INGRESO":"0"},{"@odata.etag":"","ItemInternalId":"5529050b-8283-47c3-b02c-491d27a59cf4","Año":"2025","Mes":"3","Unidad":"Minera Onoaga","RENUNCIA":"3","TERMINACIÓN DE LA OBRA O SERVICIO, O VENCIMIENTO DEL PLAZO":"0","CRS":"0","FALLECIMIENTO":"0","DESPIDO O DESTITUCIÓN (Sin Indemnización)":"1","DESPIDO EN PERIODO DE PRUEBA":"0","NO RENOVACION":"0","ANULACION DE INGRESO":"0"},{"@odata.etag":"","ItemInternalId":"067f2613-e49b-4a77-bb11-836dad2f58e2","Año":"2025","Mes":"3","Unidad":"Proyecto Puno","RENUNCIA":"0","TERMINACIÓN DE LA OBRA O SERVICIO, O VENCIMIENTO DEL PLAZO":"0","CRS":"0","FALLECIMIENTO":"0","DESPIDO O DESTITUCIÓN (Sin Indemnización)":"0","DESPIDO EN PERIODO DE PRUEBA":"0","NO RENOVACION":"0","ANULACION DE INGRESO":"0"},{"@odata.etag":"","ItemInternalId":"92b76098-dcd4-495f-a312-c56c6d291487","Año":"2025","Mes":"3","Unidad":"Proyecto Ariel","RENUNCIA":"0","TERMINACIÓN DE LA OBRA O SERVICIO, O VENCIMIENTO DEL PLAZO":"0","CRS":"0","FALLECIMIENTO":"0","DESPIDO O DESTITUCIÓN (Sin Indemnización)":"0","DESPIDO EN PERIODO DE PRUEBA":"0","NO RENOVACION":"0","ANULACION DE INGRESO":"0"},{"@odata.etag":"","ItemInternalId":"f7edb319-484a-465c-a85c-d836e5c2c364","Año":"2025","Mes":"4","Unidad":"Minera Casma","RENUNCIA":"18","TERMINACIÓN DE LA OBRA O SERVICIO, O VENCIMIENTO DEL PLAZO":"5","CRS":"0","FALLECIMIENTO":"0","DESPIDO O DESTITUCIÓN (Sin Indemnización)":"4","DESPIDO EN PERIODO DE PRUEBA":"2","NO RENOVACION":"0","ANULACION DE INGRESO":"0"},{"@odata.etag":"","ItemInternalId":"d12375ca-5bb8-4e7d-9374-858c363429ab","Año":"2025","Mes":"4","Unidad":"Sede Mina","RENUNCIA":"4","TERMINACIÓN DE LA OBRA O SERVICIO, O VENCIMIENTO DEL PLAZO":"0","CRS":"0","FALLECIMIENTO":"0","DESPIDO O DESTITUCIÓN (Sin Indemnización)":"0","DESPIDO EN PERIODO DE PRUEBA":"1","NO RENOVACION":"0","ANULACION DE INGRESO":"0"},{"@odata.etag":"","ItemInternalId":"aba428eb-2f04-4c64-b47d-d56c967e2f53","Año":"2025","Mes":"4","Unidad":"Planta Beneficio","RENUNCIA":"3","TERMINACIÓN DE LA OBRA O SERVICIO, O VENCIMIENTO DEL PLAZO":"1","CRS":"0","FALLECIMIENTO":"0","DESPIDO O DESTITUCIÓN (Sin Indemnización)":"1","DESPIDO EN PERIODO DE PRUEBA":"0","NO RENOVACION":"0","ANULACION DE INGRESO":"0"},{"@odata.etag":"","ItemInternalId":"95fc946f-4d4f-4192-8893-0c287e84aa92","Año":"2025","Mes":"4","Unidad":"Minera Onoaga","RENUNCIA":"4","TERMINACIÓN DE LA OBRA O SERVICIO, O VENCIMIENTO DEL PLAZO":"0","CRS":"0","FALLECIMIENTO":"0","DESPIDO O DESTITUCIÓN (Sin Indemnización)":"1","DESPIDO EN PERIODO DE PRUEBA":"0","NO RENOVACION":"0","ANULACION DE INGRESO":"0"},{"@odata.etag":"","ItemInternalId":"68c5ba1b-9d4a-4cfe-9de7-e4c21ad2abfb","Año":"2025","Mes":"4","Unidad":"Proyecto Puno","RENUNCIA":"0","TERMINACIÓN DE LA OBRA O SERVICIO, O VENCIMIENTO DEL PLAZO":"0","CRS":"0","FALLECIMIENTO":"0","DESPIDO O DESTITUCIÓN (Sin Indemnización)":"0","DESPIDO EN PERIODO DE PRUEBA":"0","NO RENOVACION":"0","ANULACION DE INGRESO":"0"},{"@odata.etag":"","ItemInternalId":"e3ea994c-74cc-48cf-a79d-ee6b5ed6c4d1","Año":"2025","Mes":"4","Unidad":"Proyecto Ariel","RENUNCIA":"0","TERMINACIÓN DE LA OBRA O SERVICIO, O VENCIMIENTO DEL PLAZO":"0","CRS":"0","FALLECIMIENTO":"0","DESPIDO O DESTITUCIÓN (Sin Indemnización)":"0","DESPIDO EN PERIODO DE PRUEBA":"0","NO RENOVACION":"0","ANULACION DE INGRESO":"0"},{"@odata.etag":"","ItemInternalId":"6cbffea4-a18e-413a-b248-cc8daf8f0de5","Año":"2025","Mes":"5","Unidad":"Minera Casma","RENUNCIA":"29","TERMINACIÓN DE LA OBRA O SERVICIO, O VENCIMIENTO DEL PLAZO":"1","CRS":"0","FALLECIMIENTO":"0","DESPIDO O DESTITUCIÓN (Sin Indemnización)":"0","DESPIDO EN PERIODO DE PRUEBA":"2","NO RENOVACION":"2","ANULACION DE INGRESO":"0"},{"@odata.etag":"","ItemInternalId":"a7327b4d-27f3-46f0-b60b-7fb96efa9a3d","Año":"2025","Mes":"5","Unidad":"Sede Mina","RENUNCIA":"9","TERMINACIÓN DE LA OBRA O SERVICIO, O VENCIMIENTO DEL PLAZO":"0","CRS":"0","FALLECIMIENTO":"0","DESPIDO O DESTITUCIÓN (Sin Indemnización)":"0","DESPIDO EN PERIODO DE PRUEBA":"0","NO RENOVACION":"0","ANULACION DE INGRESO":"0"},{"@odata.etag":"","ItemInternalId":"9a482eba-5452-4c8b-b1aa-0ebfd53b476f","Año":"2025","Mes":"5","Unidad":"Planta Beneficio","RENUNCIA":"9","TERMINACIÓN DE LA OBRA O SERVICIO, O VENCIMIENTO DEL PLAZO":"0","CRS":"0","FALLECIMIENTO":"0","DESPIDO O DESTITUCIÓN (Sin Indemnización)":"0","DESPIDO EN PERIODO DE PRUEBA":"1","NO RENOVACION":"0","ANULACION DE INGRESO":"0"},{"@odata.etag":"","ItemInternalId":"ae213b0f-b1a5-4618-be58-a678be20fb8f","Año":"2025","Mes":"5","Unidad":"Minera Onoaga","RENUNCIA":"1","TERMINACIÓN DE LA OBRA O SERVICIO, O VENCIMIENTO DEL PLAZO":"1","CRS":"0","FALLECIMIENTO":"0","DESPIDO O DESTITUCIÓN (Sin Indemnización)":"0","DESPIDO EN PERIODO DE PRUEBA":"0","NO RENOVACION":"0","ANULACION DE INGRESO":"0"},{"@odata.etag":"","ItemInternalId":"9f57cd7c-64d9-4920-9cd4-3752e54e8d67","Año":"2025","Mes":"5","Unidad":"Proyecto Puno","RENUNCIA":"0","TERMINACIÓN DE LA OBRA O SERVICIO, O VENCIMIENTO DEL PLAZO":"0","CRS":"0","FALLECIMIENTO":"0","DESPIDO O DESTITUCIÓN (Sin Indemnización)":"0","DESPIDO EN PERIODO DE PRUEBA":"0","NO RENOVACION":"0","ANULACION DE INGRESO":"0"},{"@odata.etag":"","ItemInternalId":"1880a0fa-0dbf-49d9-924b-57782807559b","Año":"2025","Mes":"5","Unidad":"Proyecto Ariel","RENUNCIA":"0","TERMINACIÓN DE LA OBRA O SERVICIO, O VENCIMIENTO DEL PLAZO":"0","CRS":"0","FALLECIMIENTO":"0","DESPIDO O DESTITUCIÓN (Sin Indemnización)":"0","DESPIDO EN PERIODO DE PRUEBA":"0","NO RENOVACION":"0","ANULACION DE INGRESO":"0"},{"@odata.etag":"","ItemInternalId":"a2c7dc01-a84e-466a-9d6c-81172b93210a","Año":"2025","Mes":"6","Unidad":"Minera Casma","RENUNCIA":"15","TERMINACIÓN DE LA OBRA O SERVICIO, O VENCIMIENTO DEL PLAZO":"1","CRS":"0","FALLECIMIENTO":"0","DESPIDO O DESTITUCIÓN (Sin Indemnización)":"1","DESPIDO EN PERIODO DE PRUEBA":"0","NO RENOVACION":"0","ANULACION DE INGRESO":"0"},{"@odata.etag":"","ItemInternalId":"77767d90-ceb8-4667-aa10-cb2a1afb6962","Año":"2025","Mes":"6","Unidad":"Sede Mina","RENUNCIA":"2","TERMINACIÓN DE LA OBRA O SERVICIO, O VENCIMIENTO DEL PLAZO":"1","CRS":"0","FALLECIMIENTO":"0","DESPIDO O DESTITUCIÓN (Sin Indemnización)":"0","DESPIDO EN PERIODO DE PRUEBA":"0","NO RENOVACION":"0","ANULACION DE INGRESO":"0"},{"@odata.etag":"","ItemInternalId":"7c7b9e22-7ef8-40d0-acca-6f75929a4314","Año":"2025","Mes":"6","Unidad":"Planta Beneficio","RENUNCIA":"6","TERMINACIÓN DE LA OBRA O SERVICIO, O VENCIMIENTO DEL PLAZO":"0","CRS":"0","FALLECIMIENTO":"0","DESPIDO O DESTITUCIÓN (Sin Indemnización)":"0","DESPIDO EN PERIODO DE PRUEBA":"0","NO RENOVACION":"0","ANULACION DE INGRESO":"0"},{"@odata.etag":"","ItemInternalId":"6fd53d2f-fe2a-4c42-b2ba-b914c0bdf7e3","Año":"2025","Mes":"6","Unidad":"Minera Onoaga","RENUNCIA":"0","TERMINACIÓN DE LA OBRA O SERVICIO, O VENCIMIENTO DEL PLAZO":"0","CRS":"0","FALLECIMIENTO":"0","DESPIDO O DESTITUCIÓN (Sin Indemnización)":"0","DESPIDO EN PERIODO DE PRUEBA":"0","NO RENOVACION":"0","ANULACION DE INGRESO":"0"},{"@odata.etag":"","ItemInternalId":"ffe33d11-f86c-4277-a2b8-261b8a3ed374","Año":"2025","Mes":"6","Unidad":"Proyecto Puno","RENUNCIA":"0","TERMINACIÓN DE LA OBRA O SERVICIO, O VENCIMIENTO DEL PLAZO":"0","CRS":"0","FALLECIMIENTO":"0","DESPIDO O DESTITUCIÓN (Sin Indemnización)":"0","DESPIDO EN PERIODO DE PRUEBA":"0","NO RENOVACION":"0","ANULACION DE INGRESO":"0"},{"@odata.etag":"","ItemInternalId":"7a8612fc-a62a-4e0a-b2eb-80b1b7d0acd2","Año":"2025","Mes":"6","Unidad":"Proyecto Ariel","RENUNCIA":"0","TERMINACIÓN DE LA OBRA O SERVICIO, O VENCIMIENTO DEL PLAZO":"0","CRS":"0","FALLECIMIENTO":"0","DESPIDO O DESTITUCIÓN (Sin Indemnización)":"0","DESPIDO EN PERIODO DE PRUEBA":"0","NO RENOVACION":"0","ANULACION DE INGRESO":"0"},{"@odata.etag":"","ItemInternalId":"49a81c90-90dc-485e-bc2a-6919458638c7","Año":"2025","Mes":"7","Unidad":"Minera Casma","RENUNCIA":"26","TERMINACIÓN DE LA OBRA O SERVICIO, O VENCIMIENTO DEL PLAZO":"9","CRS":"0","FALLECIMIENTO":"0","DESPIDO O DESTITUCIÓN (Sin Indemnización)":"3","DESPIDO EN PERIODO DE PRUEBA":"0","NO RENOVACION":"0","ANULACION DE INGRESO":"0"},{"@odata.etag":"","ItemInternalId":"405681cb-5549-42ed-9dcf-7cd01520d8c7","Año":"2025","Mes":"7","Unidad":"Sede Mina","RENUNCIA":"2","TERMINACIÓN DE LA OBRA O SERVICIO, O VENCIMIENTO DEL PLAZO":"0","CRS":"0","FALLECIMIENTO":"0","DESPIDO O DESTITUCIÓN (Sin Indemnización)":"0","DESPIDO EN PERIODO DE PRUEBA":"0","NO RENOVACION":"0","ANULACION DE INGRESO":"0"},{"@odata.etag":"","ItemInternalId":"5470ce34-6920-4e0e-9205-dd35746d8346","Año":"2025","Mes":"7","Unidad":"Planta Beneficio","RENUNCIA":"5","TERMINACIÓN DE LA OBRA O SERVICIO, O VENCIMIENTO DEL PLAZO":"2","CRS":"0","FALLECIMIENTO":"1","DESPIDO O DESTITUCIÓN (Sin Indemnización)":"0","DESPIDO EN PERIODO DE PRUEBA":"0","NO RENOVACION":"0","ANULACION DE INGRESO":"0"},{"@odata.etag":"","ItemInternalId":"a2d5d772-e6b6-4877-8028-5eaa5bc918c3","Año":"2025","Mes":"7","Unidad":"Minera Onoaga","RENUNCIA":"3","TERMINACIÓN DE LA OBRA O SERVICIO, O VENCIMIENTO DEL PLAZO":"0","CRS":"0","FALLECIMIENTO":"0","DESPIDO O DESTITUCIÓN (Sin Indemnización)":"0","DESPIDO EN PERIODO DE PRUEBA":"0","NO RENOVACION":"0","ANULACION DE INGRESO":"0"},{"@odata.etag":"","ItemInternalId":"e36fad8d-663f-4a22-958a-d14ad5e95515","Año":"2025","Mes":"7","Unidad":"Proyecto Puno","RENUNCIA":"0","TERMINACIÓN DE LA OBRA O SERVICIO, O VENCIMIENTO DEL PLAZO":"0","CRS":"0","FALLECIMIENTO":"0","DESPIDO O DESTITUCIÓN (Sin Indemnización)":"0","DESPIDO EN PERIODO DE PRUEBA":"0","NO RENOVACION":"0","ANULACION DE INGRESO":"0"},{"@odata.etag":"","ItemInternalId":"40432f0a-cad7-4090-9883-0c16af980782","Año":"2025","Mes":"7","Unidad":"Proyecto Ariel","RENUNCIA":"0","TERMINACIÓN DE LA OBRA O SERVICIO, O VENCIMIENTO DEL PLAZO":"0","CRS":"0","FALLECIMIENTO":"0","DESPIDO O DESTITUCIÓN (Sin Indemnización)":"0","DESPIDO EN PERIODO DE PRUEBA":"0","NO RENOVACION":"0","ANULACION DE INGRESO":"0"},{"@odata.etag":"","ItemInternalId":"25e76711-2a9c-4650-8f94-37c2c88513de","Año":"2025","Mes":"8","Unidad":"Minera Casma","RENUNCIA":"38","TERMINACIÓN DE LA OBRA O SERVICIO, O VENCIMIENTO DEL PLAZO":"3","CRS":"0","FALLECIMIENTO":"0","DESPIDO O DESTITUCIÓN (Sin Indemnización)":"3","DESPIDO EN PERIODO DE PRUEBA":"0","NO RENOVACION":"0","ANULACION DE INGRESO":"0"},{"@odata.etag":"","ItemInternalId":"ef20d161-12c9-492f-828d-bba85dd22410","Año":"2025","Mes":"8","Unidad":"Sede Mina","RENUNCIA":"3","TERMINACIÓN DE LA OBRA O SERVICIO, O VENCIMIENTO DEL PLAZO":"1","CRS":"0","FALLECIMIENTO":"0","DESPIDO O DESTITUCIÓN (Sin Indemnización)":"0","DESPIDO EN PERIODO DE PRUEBA":"0","NO RENOVACION":"0","ANULACION DE INGRESO":"0"},{"@odata.etag":"","ItemInternalId":"fdf8b08f-cd04-4ade-9f90-4e9a6180d1b0","Año":"2025","Mes":"8","Unidad":"Planta Beneficio","RENUNCIA":"10","TERMINACIÓN DE LA OBRA O SERVICIO, O VENCIMIENTO DEL PLAZO":"1","CRS":"0","FALLECIMIENTO":"0","DESPIDO O DESTITUCIÓN (Sin Indemnización)":"0","DESPIDO EN PERIODO DE PRUEBA":"0","NO RENOVACION":"0","ANULACION DE INGRESO":"0"},{"@odata.etag":"","ItemInternalId":"635c2d02-150e-45ec-9275-5f64c072f272","Año":"2025","Mes":"8","Unidad":"Minera Onoaga","RENUNCIA":"4","TERMINACIÓN DE LA OBRA O SERVICIO, O VENCIMIENTO DEL PLAZO":"1","CRS":"0","FALLECIMIENTO":"0","DESPIDO O DESTITUCIÓN (Sin Indemnización)":"1","DESPIDO EN PERIODO DE PRUEBA":"0","NO RENOVACION":"0","ANULACION DE INGRESO":"0"},{"@odata.etag":"","ItemInternalId":"0504699a-4880-4081-ade2-4a89280ddacf","Año":"2025","Mes":"8","Unidad":"Proyecto Puno","RENUNCIA":"1","TERMINACIÓN DE LA OBRA O SERVICIO, O VENCIMIENTO DEL PLAZO":"0","CRS":"0","FALLECIMIENTO":"0","DESPIDO O DESTITUCIÓN (Sin Indemnización)":"0","DESPIDO EN PERIODO DE PRUEBA":"0","NO RENOVACION":"0","ANULACION DE INGRESO":"0"},{"@odata.etag":"","ItemInternalId":"fb309763-8cb4-4342-afa7-83d35a5a320a","Año":"2025","Mes":"8","Unidad":"Proyecto Ariel","RENUNCIA":"0","TERMINACIÓN DE LA OBRA O SERVICIO, O VENCIMIENTO DEL PLAZO":"0","CRS":"0","FALLECIMIENTO":"0","DESPIDO O DESTITUCIÓN (Sin Indemnización)":"0","DESPIDO EN PERIODO DE PRUEBA":"0","NO RENOVACION":"0","ANULACION DE INGRESO":"0"},{"@odata.etag":"","ItemInternalId":"e7814bbf-e927-45c1-934d-25fd8408f3d4","Año":"2025","Mes":"9","Unidad":"Minera Casma","RENUNCIA":"18","TERMINACIÓN DE LA OBRA O SERVICIO, O VENCIMIENTO DEL PLAZO":"4","CRS":"0","FALLECIMIENTO":"0","DESPIDO O DESTITUCIÓN (Sin Indemnización)":"5","DESPIDO EN PERIODO DE PRUEBA":"0","NO RENOVACION":"0","ANULACION DE INGRESO":"0"},{"@odata.etag":"","ItemInternalId":"67e7ebab-4820-4a0f-b83f-fa0ed6169d0c","Año":"2025","Mes":"9","Unidad":"Sede Mina","RENUNCIA":"11","TERMINACIÓN DE LA OBRA O SERVICIO, O VENCIMIENTO DEL PLAZO":"0","CRS":"0","FALLECIMIENTO":"0","DESPIDO O DESTITUCIÓN (Sin Indemnización)":"1","DESPIDO EN PERIODO DE PRUEBA":"0","NO RENOVACION":"0","ANULACION DE INGRESO":"0"},{"@odata.etag":"","ItemInternalId":"2db0c103-d4c1-4cee-bcab-48182405b6cf","Año":"2025","Mes":"9","Unidad":"Planta Beneficio","RENUNCIA":"0","TERMINACIÓN DE LA OBRA O SERVICIO, O VENCIMIENTO DEL PLAZO":"0","CRS":"0","FALLECIMIENTO":"0","DESPIDO O DESTITUCIÓN (Sin Indemnización)":"0","DESPIDO EN PERIODO DE PRUEBA":"0","NO RENOVACION":"0","ANULACION DE INGRESO":"0"},{"@odata.etag":"","ItemInternalId":"6235e547-eea1-4e6f-ab07-a5c5154be83a","Año":"2025","Mes":"9","Unidad":"Minera Onoaga","RENUNCIA":"1","TERMINACIÓN DE LA OBRA O SERVICIO, O VENCIMIENTO DEL PLAZO":"1","CRS":"0","FALLECIMIENTO":"0","DESPIDO O DESTITUCIÓN (Sin Indemnización)":"1","DESPIDO EN PERIODO DE PRUEBA":"0","NO RENOVACION":"0","ANULACION DE INGRESO":"0"},{"@odata.etag":"","ItemInternalId":"89e85311-1782-48ca-88c6-77e425be8bde","Año":"2025","Mes":"9","Unidad":"Proyecto Puno","RENUNCIA":"1","TERMINACIÓN DE LA OBRA O SERVICIO, O VENCIMIENTO DEL PLAZO":"0","CRS":"0","FALLECIMIENTO":"0","DESPIDO O DESTITUCIÓN (Sin Indemnización)":"0","DESPIDO EN PERIODO DE PRUEBA":"0","NO RENOVACION":"0","ANULACION DE INGRESO":"0"},{"@odata.etag":"","ItemInternalId":"596d6810-6bf7-40db-b316-00a5f76b8594","Año":"2025","Mes":"9","Unidad":"Proyecto Ariel","RENUNCIA":"0","TERMINACIÓN DE LA OBRA O SERVICIO, O VENCIMIENTO DEL PLAZO":"0","CRS":"0","FALLECIMIENTO":"0","DESPIDO O DESTITUCIÓN (Sin Indemnización)":"0","DESPIDO EN PERIODO DE PRUEBA":"0","NO RENOVACION":"0","ANULACION DE INGRESO":"0"},{"@odata.etag":"","ItemInternalId":"55162959-7f36-49d9-b672-79c4e946710b","Año":"2025","Mes":"10","Unidad":"Minera Casma","RENUNCIA":"30","TERMINACIÓN DE LA OBRA O SERVICIO, O VENCIMIENTO DEL PLAZO":"10","CRS":"0","FALLECIMIENTO":"0","DESPIDO O DESTITUCIÓN (Sin Indemnización)":"4","DESPIDO EN PERIODO DE PRUEBA":"0","NO RENOVACION":"0","ANULACION DE INGRESO":"0"},{"@odata.etag":"","ItemInternalId":"7890f01e-3082-4af4-939e-f1e1c44d2251","Año":"2025","Mes":"10","Unidad":"Sede Mina","RENUNCIA":"2","TERMINACIÓN DE LA OBRA O SERVICIO, O VENCIMIENTO DEL PLAZO":"0","CRS":"0","FALLECIMIENTO":"0","DESPIDO O DESTITUCIÓN (Sin Indemnización)":"2","DESPIDO EN PERIODO DE PRUEBA":"0","NO RENOVACION":"0","ANULACION DE INGRESO":"0"},{"@odata.etag":"","ItemInternalId":"f538520b-2f3d-4217-b5be-47b854195700","Año":"2025","Mes":"10","Unidad":"Planta Beneficio","RENUNCIA":"4","TERMINACIÓN DE LA OBRA O SERVICIO, O VENCIMIENTO DEL PLAZO":"5","CRS":"0","FALLECIMIENTO":"0","DESPIDO O DESTITUCIÓN (Sin Indemnización)":"0","DESPIDO EN PERIODO DE PRUEBA":"0","NO RENOVACION":"0","ANULACION DE INGRESO":"0"},{"@odata.etag":"","ItemInternalId":"3e30f0c9-0710-4b1f-954a-40515f421f0d","Año":"2025","Mes":"10","Unidad":"Minera Onoaga","RENUNCIA":"1","TERMINACIÓN DE LA OBRA O SERVICIO, O VENCIMIENTO DEL PLAZO":"1","CRS":"0","FALLECIMIENTO":"0","DESPIDO O DESTITUCIÓN (Sin Indemnización)":"0","DESPIDO EN PERIODO DE PRUEBA":"0","NO RENOVACION":"0","ANULACION DE INGRESO":"0"},{"@odata.etag":"","ItemInternalId":"c4f58ce3-3820-4327-b79e-dd603f7abbd3","Año":"2025","Mes":"10","Unidad":"Proyecto Puno","RENUNCIA":"0","TERMINACIÓN DE LA OBRA O SERVICIO, O VENCIMIENTO DEL PLAZO":"0","CRS":"0","FALLECIMIENTO":"0","DESPIDO O DESTITUCIÓN (Sin Indemnización)":"0","DESPIDO EN PERIODO DE PRUEBA":"0","NO RENOVACION":"0","ANULACION DE INGRESO":"0"},{"@odata.etag":"","ItemInternalId":"943abe44-1da0-43be-b11c-3991f32e2854","Año":"2025","Mes":"10","Unidad":"Proyecto Ariel","RENUNCIA":"0","TERMINACIÓN DE LA OBRA O SERVICIO, O VENCIMIENTO DEL PLAZO":"0","CRS":"0","FALLECIMIENTO":"0","DESPIDO O DESTITUCIÓN (Sin Indemnización)":"0","DESPIDO EN PERIODO DE PRUEBA":"0","NO RENOVACION":"0","ANULACION DE INGRESO":"0"},{"@odata.etag":"","ItemInternalId":"e5c476c7-13b2-42f4-a5dd-227e9d5bbada","Año":"2025","Mes":"11","Unidad":"Minera Casma","RENUNCIA":"22","TERMINACIÓN DE LA OBRA O SERVICIO, O VENCIMIENTO DEL PLAZO":"11","CRS":"0","FALLECIMIENTO":"0","DESPIDO O DESTITUCIÓN (Sin Indemnización)":"4","DESPIDO EN PERIODO DE PRUEBA":"0","NO RENOVACION":"0","ANULACION DE INGRESO":"0"},{"@odata.etag":"","ItemInternalId":"ea3bcc31-dec0-48f2-a697-5ed82055c98c","Año":"2025","Mes":"11","Unidad":"Sede Mina","RENUNCIA":"2","TERMINACIÓN DE LA OBRA O SERVICIO, O VENCIMIENTO DEL PLAZO":"0","CRS":"0","FALLECIMIENTO":"0","DESPIDO O DESTITUCIÓN (Sin Indemnización)":"0","DESPIDO EN PERIODO DE PRUEBA":"0","NO RENOVACION":"0","ANULACION DE INGRESO":"0"},{"@odata.etag":"","ItemInternalId":"deb861f6-2af5-4448-9c65-39f5acb8559b","Año":"2025","Mes":"11","Unidad":"Planta Beneficio","RENUNCIA":"5","TERMINACIÓN DE LA OBRA O SERVICIO, O VENCIMIENTO DEL PLAZO":"2","CRS":"0","FALLECIMIENTO":"0","DESPIDO O DESTITUCIÓN (Sin Indemnización)":"0","DESPIDO EN PERIODO DE PRUEBA":"0","NO RENOVACION":"0","ANULACION DE INGRESO":"0"},{"@odata.etag":"","ItemInternalId":"8cbaf201-76c1-4711-81a6-846c54b53095","Año":"2025","Mes":"11","Unidad":"Minera Onoaga","RENUNCIA":"4","TERMINACIÓN DE LA OBRA O SERVICIO, O VENCIMIENTO DEL PLAZO":"1","CRS":"0","FALLECIMIENTO":"0","DESPIDO O DESTITUCIÓN (Sin Indemnización)":"0","DESPIDO EN PERIODO DE PRUEBA":"1","NO RENOVACION":"0","ANULACION DE INGRESO":"0"},{"@odata.etag":"","ItemInternalId":"49c93cd4-5366-4071-8405-db984db97c25","Año":"2025","Mes":"11","Unidad":"Proyecto Puno","RENUNCIA":"0","TERMINACIÓN DE LA OBRA O SERVICIO, O VENCIMIENTO DEL PLAZO":"0","CRS":"0","FALLECIMIENTO":"0","DESPIDO O DESTITUCIÓN (Sin Indemnización)":"0","DESPIDO EN PERIODO DE PRUEBA":"0","NO RENOVACION":"0","ANULACION DE INGRESO":"0"},{"@odata.etag":"","ItemInternalId":"2389fa03-d098-44c6-8f6e-ed96e6227c39","Año":"2025","Mes":"11","Unidad":"Proyecto Ariel","RENUNCIA":"0","TERMINACIÓN DE LA OBRA O SERVICIO, O VENCIMIENTO DEL PLAZO":"0","CRS":"0","FALLECIMIENTO":"0","DESPIDO O DESTITUCIÓN (Sin Indemnización)":"0","DESPIDO EN PERIODO DE PRUEBA":"0","NO RENOVACION":"0","ANULACION DE INGRESO":"0"},{"@odata.etag":"","ItemInternalId":"5557d203-f001-45c0-991d-40b214885aad","Año":"2025","Mes":"12","Unidad":"Minera Casma","RENUNCIA":"42","TERMINACIÓN DE LA OBRA O SERVICIO, O VENCIMIENTO DEL PLAZO":"17","CRS":"0","FALLECIMIENTO":"0","DESPIDO O DESTITUCIÓN (Sin Indemnización)":"2","DESPIDO EN PERIODO DE PRUEBA":"0","NO RENOVACION":"0","ANULACION DE INGRESO":"0"},{"@odata.etag":"","ItemInternalId":"c12e1d6c-2e2a-4f55-b1c9-88c1c647ff56","Año":"2025","Mes":"12","Unidad":"Sede Mina","RENUNCIA":"6","TERMINACIÓN DE LA OBRA O SERVICIO, O VENCIMIENTO DEL PLAZO":"3","CRS":"0","FALLECIMIENTO":"0","DESPIDO O DESTITUCIÓN (Sin Indemnización)":"0","DESPIDO EN PERIODO DE PRUEBA":"0","NO RENOVACION":"0","ANULACION DE INGRESO":"0"},{"@odata.etag":"","ItemInternalId":"4757b80b-8e88-40a8-9ade-cc37530468a6","Año":"2025","Mes":"12","Unidad":"Planta Beneficio","RENUNCIA":"2","TERMINACIÓN DE LA OBRA O SERVICIO, O VENCIMIENTO DEL PLAZO":"1","CRS":"0","FALLECIMIENTO":"0","DESPIDO O DESTITUCIÓN (Sin Indemnización)":"0","DESPIDO EN PERIODO DE PRUEBA":"0","NO RENOVACION":"0","ANULACION DE INGRESO":"0"},{"@odata.etag":"","ItemInternalId":"81d382bd-12fd-4066-8c2e-c90aae5b9ea4","Año":"2025","Mes":"12","Unidad":"Minera Onoaga","RENUNCIA":"2","TERMINACIÓN DE LA OBRA O SERVICIO, O VENCIMIENTO DEL PLAZO":"0","CRS":"0","FALLECIMIENTO":"0","DESPIDO O DESTITUCIÓN (Sin Indemnización)":"1","DESPIDO EN PERIODO DE PRUEBA":"0","NO RENOVACION":"0","ANULACION DE INGRESO":"0"},{"@odata.etag":"","ItemInternalId":"1156f584-e6bc-43bb-9c72-6ea1cee770a0","Año":"2025","Mes":"12","Unidad":"Proyecto Puno","RENUNCIA":"0","TERMINACIÓN DE LA OBRA O SERVICIO, O VENCIMIENTO DEL PLAZO":"0","CRS":"0","FALLECIMIENTO":"0","DESPIDO O DESTITUCIÓN (Sin Indemnización)":"0","DESPIDO EN PERIODO DE PRUEBA":"0","NO RENOVACION":"0","ANULACION DE INGRESO":"0"},{"@odata.etag":"","ItemInternalId":"59936bbd-674c-4295-a187-72ddd5391008","Año":"2025","Mes":"12","Unidad":"Proyecto Ariel","RENUNCIA":"0","TERMINACIÓN DE LA OBRA O SERVICIO, O VENCIMIENTO DEL PLAZO":"0","CRS":"0","FALLECIMIENTO":"0","DESPIDO O DESTITUCIÓN (Sin Indemnización)":"0","DESPIDO EN PERIODO DE PRUEBA":"0","NO RENOVACION":"0","ANULACION DE INGRESO":"0"},{"@odata.etag":"","ItemInternalId":"36f21f35-16e8-4646-b63d-aa64061e0b6d","Año":"2026","Mes":"1","Unidad":"Minera Casma","RENUNCIA":"35","TERMINACIÓN DE LA OBRA O SERVICIO, O VENCIMIENTO DEL PLAZO":"7","CRS":"0","FALLECIMIENTO":"0","DESPIDO O DESTITUCIÓN (Sin Indemnización)":"2","DESPIDO EN PERIODO DE PRUEBA":"0","NO RENOVACION":"0","ANULACION DE INGRESO":"0"},{"@odata.etag":"","ItemInternalId":"cda1ef63-8281-4d19-98ff-7715435ca40a","Año":"2026","Mes":"1","Unidad":"Sede Mina","RENUNCIA":"3","TERMINACIÓN DE LA OBRA O SERVICIO, O VENCIMIENTO DEL PLAZO":"3","CRS":"0","FALLECIMIENTO":"0","DESPIDO O DESTITUCIÓN (Sin Indemnización)":"0","DESPIDO EN PERIODO DE PRUEBA":"0","NO RENOVACION":"0","ANULACION DE INGRESO":"0"},{"@odata.etag":"","ItemInternalId":"a0975a89-befb-4ba8-964f-901efe87f955","Año":"2026","Mes":"1","Unidad":"Planta Beneficio","RENUNCIA":"4","TERMINACIÓN DE LA OBRA O SERVICIO, O VENCIMIENTO DEL PLAZO":"3","CRS":"0","FALLECIMIENTO":"0","DESPIDO O DESTITUCIÓN (Sin Indemnización)":"0","DESPIDO EN PERIODO DE PRUEBA":"0","NO RENOVACION":"0","ANULACION DE INGRESO":"0"},{"@odata.etag":"","ItemInternalId":"b66d9374-2860-4d09-98fb-185105575fd3","Año":"2026","Mes":"1","Unidad":"Minera Onoaga","RENUNCIA":"6","TERMINACIÓN DE LA OBRA O SERVICIO, O VENCIMIENTO DEL PLAZO":"0","CRS":"0","FALLECIMIENTO":"0","DESPIDO O DESTITUCIÓN (Sin Indemnización)":"1","DESPIDO EN PERIODO DE PRUEBA":"0","NO RENOVACION":"0","ANULACION DE INGRESO":"0"},{"@odata.etag":"","ItemInternalId":"d4d54e9f-008c-4552-a3e4-193a9f4b01ef","Año":"2026","Mes":"1","Unidad":"Proyecto Puno","RENUNCIA":"1","TERMINACIÓN DE LA OBRA O SERVICIO, O VENCIMIENTO DEL PLAZO":"0","CRS":"0","FALLECIMIENTO":"0","DESPIDO O DESTITUCIÓN (Sin Indemnización)":"0","DESPIDO EN PERIODO DE PRUEBA":"0","NO RENOVACION":"0","ANULACION DE INGRESO":"0"},{"@odata.etag":"","ItemInternalId":"bcd9bf12-1aaf-4419-b0cb-c5e0b34c8c01","Año":"2026","Mes":"1","Unidad":"Proyecto Ariel","RENUNCIA":"0","TERMINACIÓN DE LA OBRA O SERVICIO, O VENCIMIENTO DEL PLAZO":"0","CRS":"0","FALLECIMIENTO":"0","DESPIDO O DESTITUCIÓN (Sin Indemnización)":"0","DESPIDO EN PERIODO DE PRUEBA":"0","NO RENOVACION":"0","ANULACION DE INGRESO":"0"},{"@odata.etag":"","ItemInternalId":"3aa837db-c0b0-4696-bd10-2f0fc571c7d7","Año":"2026","Mes":"2","Unidad":"Minera Casma","RENUNCIA":"24","TERMINACIÓN DE LA OBRA O SERVICIO, O VENCIMIENTO DEL PLAZO":"5","CRS":"0","FALLECIMIENTO":"0","DESPIDO O DESTITUCIÓN (Sin Indemnización)":"2","DESPIDO EN PERIODO DE PRUEBA":"0","NO RENOVACION":"0","ANULACION DE INGRESO":"1"},{"@odata.etag":"","ItemInternalId":"23b3d9f9-5dd8-4419-a683-4b8f9fc2bb68","Año":"2026","Mes":"2","Unidad":"Sede Mina","RENUNCIA":"0","TERMINACIÓN DE LA OBRA O SERVICIO, O VENCIMIENTO DEL PLAZO":"1","CRS":"0","FALLECIMIENTO":"0","DESPIDO O DESTITUCIÓN (Sin Indemnización)":"2","DESPIDO EN PERIODO DE PRUEBA":"0","NO RENOVACION":"0","ANULACION DE INGRESO":"0"},{"@odata.etag":"","ItemInternalId":"3caa2612-9b80-4c91-85fd-691cd5cd65e1","Año":"2026","Mes":"2","Unidad":"Planta Beneficio","RENUNCIA":"4","TERMINACIÓN DE LA OBRA O SERVICIO, O VENCIMIENTO DEL PLAZO":"5","CRS":"0","FALLECIMIENTO":"0","DESPIDO O DESTITUCIÓN (Sin Indemnización)":"0","DESPIDO EN PERIODO DE PRUEBA":"0","NO RENOVACION":"0","ANULACION DE INGRESO":"0"},{"@odata.etag":"","ItemInternalId":"426ea509-5b35-4fdb-9b20-8734ab83e328","Año":"2026","Mes":"2","Unidad":"Minera Onoaga","RENUNCIA":"7","TERMINACIÓN DE LA OBRA O SERVICIO, O VENCIMIENTO DEL PLAZO":"0","CRS":"0","FALLECIMIENTO":"0","DESPIDO O DESTITUCIÓN (Sin Indemnización)":"0","DESPIDO EN PERIODO DE PRUEBA":"0","NO RENOVACION":"0","ANULACION DE INGRESO":"0"},{"@odata.etag":"","ItemInternalId":"9c9e3d61-72b7-4d26-a64c-31046e4e375c","Año":"2026","Mes":"2","Unidad":"Proyecto Puno","RENUNCIA":"0","TERMINACIÓN DE LA OBRA O SERVICIO, O VENCIMIENTO DEL PLAZO":"0","CRS":"0","FALLECIMIENTO":"0","DESPIDO O DESTITUCIÓN (Sin Indemnización)":"0","DESPIDO EN PERIODO DE PRUEBA":"0","NO RENOVACION":"0","ANULACION DE INGRESO":"0"},{"@odata.etag":"","ItemInternalId":"b0325273-2299-4c65-8873-884e7ec3daaa","Año":"2026","Mes":"2","Unidad":"Proyecto Ariel","RENUNCIA":"0","TERMINACIÓN DE LA OBRA O SERVICIO, O VENCIMIENTO DEL PLAZO":"0","CRS":"0","FALLECIMIENTO":"0","DESPIDO O DESTITUCIÓN (Sin Indemnización)":"0","DESPIDO EN PERIODO DE PRUEBA":"0","NO RENOVACION":"0","ANULACION DE INGRESO":"0"},{"@odata.etag":"","ItemInternalId":"3b74ec0c-be5c-4046-aee2-00a8bd926c52","Año":"2026","Mes":"3","Unidad":"Minera Casma","RENUNCIA":"31","TERMINACIÓN DE LA OBRA O SERVICIO, O VENCIMIENTO DEL PLAZO":"4","CRS":"0","FALLECIMIENTO":"0","DESPIDO O DESTITUCIÓN (Sin Indemnización)":"8","DESPIDO EN PERIODO DE PRUEBA":"0","NO RENOVACION":"0","ANULACION DE INGRESO":"0"},{"@odata.etag":"","ItemInternalId":"9e766d6f-1ef7-4ba4-bfb2-8b475dd8c12f","Año":"2026","Mes":"3","Unidad":"Sede Mina","RENUNCIA":"2","TERMINACIÓN DE LA OBRA O SERVICIO, O VENCIMIENTO DEL PLAZO":"1","CRS":"0","FALLECIMIENTO":"0","DESPIDO O DESTITUCIÓN (Sin Indemnización)":"0","DESPIDO EN PERIODO DE PRUEBA":"0","NO RENOVACION":"0","ANULACION DE INGRESO":"0"},{"@odata.etag":"","ItemInternalId":"12d9dbd0-6beb-44ad-be69-bab7f666105a","Año":"2026","Mes":"3","Unidad":"Planta Beneficio","RENUNCIA":"7","TERMINACIÓN DE LA OBRA O SERVICIO, O VENCIMIENTO DEL PLAZO":"1","CRS":"0","FALLECIMIENTO":"0","DESPIDO O DESTITUCIÓN (Sin Indemnización)":"0","DESPIDO EN PERIODO DE PRUEBA":"0","NO RENOVACION":"0","ANULACION DE INGRESO":"0"},{"@odata.etag":"","ItemInternalId":"943de570-082b-4aa4-90dc-6f10f0d1d169","Año":"2026","Mes":"3","Unidad":"Minera Onoaga","RENUNCIA":"9","TERMINACIÓN DE LA OBRA O SERVICIO, O VENCIMIENTO DEL PLAZO":"0","CRS":"0","FALLECIMIENTO":"0","DESPIDO O DESTITUCIÓN (Sin Indemnización)":"1","DESPIDO EN PERIODO DE PRUEBA":"0","NO RENOVACION":"0","ANULACION DE INGRESO":"0"},{"@odata.etag":"","ItemInternalId":"8ad3bd4f-5edb-44ac-8077-731576fa9b11","Año":"2026","Mes":"3","Unidad":"Proyecto Puno","RENUNCIA":"0","TERMINACIÓN DE LA OBRA O SERVICIO, O VENCIMIENTO DEL PLAZO":"0","CRS":"0","FALLECIMIENTO":"0","DESPIDO O DESTITUCIÓN (Sin Indemnización)":"0","DESPIDO EN PERIODO DE PRUEBA":"0","NO RENOVACION":"0","ANULACION DE INGRESO":"0"},{"@odata.etag":"","ItemInternalId":"c5011a22-92f9-4317-a662-25352625b153","Año":"2026","Mes":"3","Unidad":"Proyecto Ariel","RENUNCIA":"0","TERMINACIÓN DE LA OBRA O SERVICIO, O VENCIMIENTO DEL PLAZO":"0","CRS":"0","FALLECIMIENTO":"0","DESPIDO O DESTITUCIÓN (Sin Indemnización)":"0","DESPIDO EN PERIODO DE PRUEBA":"0","NO RENOVACION":"0","ANULACION DE INGRESO":"0"},{"@odata.etag":"","ItemInternalId":"dab2e7b7-cfcd-499a-afa0-4a153b91573b","Año":"2026","Mes":"4","Unidad":"Minera Casma","RENUNCIA":"22","TERMINACIÓN DE LA OBRA O SERVICIO, O VENCIMIENTO DEL PLAZO":"0","CRS":"0","FALLECIMIENTO":"0","DESPIDO O DESTITUCIÓN (Sin Indemnización)":"9","DESPIDO EN PERIODO DE PRUEBA":"0","NO RENOVACION":"0","ANULACION DE INGRESO":"0"},{"@odata.etag":"","ItemInternalId":"f9e8be11-1308-4577-9c7f-619ffde04c8a","Año":"2026","Mes":"4","Unidad":"Sede Mina","RENUNCIA":"2","TERMINACIÓN DE LA OBRA O SERVICIO, O VENCIMIENTO DEL PLAZO":"0","CRS":"0","FALLECIMIENTO":"0","DESPIDO O DESTITUCIÓN (Sin Indemnización)":"1","DESPIDO EN PERIODO DE PRUEBA":"0","NO RENOVACION":"0","ANULACION DE INGRESO":"0"},{"@odata.etag":"","ItemInternalId":"97135c3b-a322-4de2-b793-d2e59653968a","Año":"2026","Mes":"4","Unidad":"Planta Beneficio","RENUNCIA":"6","TERMINACIÓN DE LA OBRA O SERVICIO, O VENCIMIENTO DEL PLAZO":"0","CRS":"0","FALLECIMIENTO":"0","DESPIDO O DESTITUCIÓN (Sin Indemnización)":"0","DESPIDO EN PERIODO DE PRUEBA":"0","NO RENOVACION":"0","ANULACION DE INGRESO":"0"},{"@odata.etag":"","ItemInternalId":"5867402e-fd72-412f-91d8-3ff1c044fcc6","Año":"2026","Mes":"4","Unidad":"Minera Onoaga","RENUNCIA":"1","TERMINACIÓN DE LA OBRA O SERVICIO, O VENCIMIENTO DEL PLAZO":"0","CRS":"0","FALLECIMIENTO":"0","DESPIDO O DESTITUCIÓN (Sin Indemnización)":"0","DESPIDO EN PERIODO DE PRUEBA":"0","NO RENOVACION":"0","ANULACION DE INGRESO":"0"},{"@odata.etag":"","ItemInternalId":"efef8bba-7c08-4cae-b6f7-991eb726e540","Año":"2026","Mes":"4","Unidad":"Proyecto Puno","RENUNCIA":"0","TERMINACIÓN DE LA OBRA O SERVICIO, O VENCIMIENTO DEL PLAZO":"0","CRS":"0","FALLECIMIENTO":"0","DESPIDO O DESTITUCIÓN (Sin Indemnización)":"0","DESPIDO EN PERIODO DE PRUEBA":"0","NO RENOVACION":"0","ANULACION DE INGRESO":"0"},{"@odata.etag":"","ItemInternalId":"ca6c8e95-c304-429e-9aab-78ce5163c99a","Año":"2026","Mes":"4","Unidad":"Proyecto Ariel","RENUNCIA":"0","TERMINACIÓN DE LA OBRA O SERVICIO, O VENCIMIENTO DEL PLAZO":"0","CRS":"0","FALLECIMIENTO":"0","DESPIDO O DESTITUCIÓN (Sin Indemnización)":"0","DESPIDO EN PERIODO DE PRUEBA":"0","NO RENOVACION":"0","ANULACION DE INGRESO":"0"}]}